Workbook

Sheet Read Me
A1: US Water Infrastructure — Analysis Workbook
A2: Historical spending · forward budget model · technical drivers · Core & Main and Ferguson
A4: What this workbook contains
A5: A quantitative companion to the written analysis. Nineteen tabs covering who funds US water infrastructure, what annual spend should look like through 2035, the engineering evidence for replacement, where the underlying asset data actually lives, the full downloaded time series, and how it all flows through to the two listed distributors with direct exposure.
A7: Tab | B7: What it holds | C7: Formula-driven?
A8: Dashboard | B8: Headline figures pulled from the other tabs | C8: Yes — all links
A9: Assumptions | B9: Every model input in one place. THIS IS THE TAB TO EDIT. | C9: Inputs (blue/yellow)
A10: Forward Model | B10: National water capital spending build-up, 2026–2035 | C10: Yes
A11: Scenarios | B11: Bear / base / bull, driven off the Assumptions levers | C11: Yes
A12: Historical Spending | B12: CBO 1956–2023 series, Census construction, local capital | C12: Partly
A13: Federal Programs | B13: SRF, IIJA, WIFIA, earmarks, WRDA 2026 | C13: Partly
A14: Needs Estimates | B14: The four published studies, annualised and reconciled | C14: Yes
A15: Pipe and Assets | B15: USU break rates, miles by material, asset inventory | C15: Yes
A16: Regulatory | B16: Lead & Copper Rule Improvements, PFAS, CSO consent decrees | C16: Partly
A17: Core and Main | B17: Five-year P&L, end-market mix, guidance, derived metrics | C17: Yes
A18: Ferguson | B18: Eight-year P&L, US customer groups, waterworks estimate | C18: Yes
... A25: Sources | B25: Every source with its known interest or bias | C25: No
A27: Colour legend
A28: Format | B28: Meaning | C28: Example
A29: Blue text | B29: Hardcoded input — safe to change | C29: 68.0
A30: Black text | B30: Formula — do not overwrite | C30: SUM(B2:B9)
A31: Green text | B31: Link to another tab in this workbook | C31: 'Assumptions'!B5
A32: Yellow fill | B32: Key assumption the reader should review | C32: growth rate
A34: Method and provenance
A35: Company financials, segment mix, guidance and management quotations: sourced from Quartr — primary earnings releases, investor presentations and call transcripts. Core & Main Q1 FY2026 (10 Jun 2026) and FY2025 results (24 Mar 2026); Ferguson Q2 CY2026 (10 Aug 2026) and CY2025 transition period (24 Feb 2026).
A37: Public spending and technical data: CBO, US Census Bureau, Congressional Research Service, EPA, EPA Office of Inspector General, GAO, USGS, ASCE, AWWA, Utah State University and Bluefield Research. Each figure is attributed on its own row.
A39: Derived figures are computed by formula from cited inputs, never typed as results. Where a number is an estimate rather than a reported figure it is labelled ESTIMATE on its row.
A41: Caveats that belong on the front page
A42: DATA ACCESS. This workbook was assembled in an environment whose network policy blocked direct retrieval from cbo.gov, epa.gov, census.gov, congress.gov, fred.stlouisfed.org and infrastructurereportcard.org. Public-sector figures were obtained via search results summarising those primary documents. Attributions are to the correct primary source, but VERIFY EACH HEADLINE NUMBER against the source document before relying on it for an investment decision. Company financials do not carry this caveat — they came from Quartr's primary filings.
A44: THE CAPITAL BASE. The $68bn 2026 base on the Assumptions tab is a reconciliation of four independent sources, not a single reported figure — see the Needs Estimates tab for the derivation. An earlier draft of this analysis used $88bn, which was Census construction put in place; that series bundles solid waste with sewerage and includes private work, and overstates water capital spending by roughly 30%.
A46: NO VALUATION. This workbook contains no valuation, no price target and no recommendation. It sizes a market, models its trajectory, and tests the engineering claims underneath it.
A48: Built August 2026.

Sheet Assumptions
A1: Assumptions
A2: Blue = editable input. Every model figure elsewhere in this workbook resolves back to this tab.
A4: Core model inputs
A5: Input | B5: Value | C5: Unit | D5: Basis
A6: National water capital spending, 2026 | B6: 68 | C6: $bn | D6: Reconciliation of four sources — see Needs Estimates tab. CBO water utilities capital $59bn (2023) escalated; Census adjusted for solid-waste content; ASCE and AWWA implied.
A7: Organic growth rate, nominal | B7: 0.045 | C7: % p.a. | D7: Bluefield treatment capex CAGR 4.4%; water and sewer rate growth ~5%.
A8: IIJA gross federal step-down | B8: 8.7 | C8: $bn p.a. | D8: Annual SRF funding fell from ~$2.7bn (FY2021) to ~$11.4bn (FY2022-26) — National League of Cities.
A9: Less: permanent revolving offset | B9: 2 | C9: $bn p.a. | D9: ESTIMATE. ~50/50 grant vs loan split implies ~$25bn permanent SRF corpus supporting ongoing lending.
A10: Net steady-state IIJA drag | B10: =B8-B9 -> 6.7 | C10: $bn p.a. | D10: Formula. The figure that actually leaves the system once revolving lending is netted off.
A11: as % of the 2026 capital base | B11: =B10/B6 -> 0.098529412 | C11: % | D11: Formula. The honest measure of the funding cliff.
A13: Scenario levers
A14: Scenario | B14: Organic growth | C14: IIJA drag ($bn) | D14: Regulatory adder multiplier
A15: Bear | B15: 0.03 | C15: 9 | D15: 0.5
A16: Base | B16: =B7 -> 0.045 | C16: =B10 -> 6.7 | D16: 1
A17: Bull | B17: 0.055 | C17: 4 | D17: 1.1
A18: Bear: FY2027 House 16% SRF cut sustained, no WRDA reauthorisation, rate growth decelerates to 3%, LCRI struck down in part. Bull: WRDA 2026 appropriated in full, LCRI upheld, rate growth holds 5.5%.
A21: Year-indexed drivers
A22: Driver | B22: Unit | C22: 2026 | D22: 2027 | E22: 2028 | F22: 2029 | G22: 2030 | H22: 2031 | I22: 2032 | J22: 2033 | K22: 2034 | L22: 2035
A23: IIJA drawdown phasing | B23: % of full effect | C23: 0 | D23: 0.15 | E23: 0.4 | F23: 0.75 | G23: 1 | H23: 1 | I23: 1 | J23: 1 | K23: 1 | L23: 1
A24: Lead service line adder | B24: $bn | C24: 0 | D24: 2 | E24: 3.5 | F24: 5 | G24: 5.5 | H24: 5.5 | I24: 5 | J24: 4.5 | K24: 3.5 | L24: 2
A25: PFAS adder | B25: $bn | C25: 0 | D25: 1 | E25: 1.8 | F25: 2.5 | G25: 2.5 | H25: 2 | I25: 1.5 | J25: 1.2 | K25: 1 | L25: 1
A27: Phasing: only about a third of the ~$50bn IIJA water money had reached municipalities by mid-2026 (Core & Main, Q1 FY2026 call), so the drawdown lands across 2027-2030 rather than at expiry.
A28: Lead adder: 9.2m lines at $4,700-$6,930 each (EPA) over the LCRI ten-year window, net of the $15bn of dedicated IIJA funding already inside the base.
A29: PFAS adder: incremental capital and O&M above base. EPA's 18 May 2026 proposal retains only PFOA and PFOS and would slip compliance to 2031, so spend shifts right and the peak is lower than the 2024 six-compound rule implied.

Sheet Forward Model
A1: Forward Model — National Water Capital Spending
A2: $bn nominal. Every cell is a formula off the Assumptions tab.
A4: Line | B4: Basis | C4: 2026 | D4: 2027 | E4: 2028 | F4: 2029 | G4: 2030 | H4: 2031 | I4: 2032 | J4: 2033 | K4: 2034 | L4: 2035
A5: Organic base | B5: grows at assumed rate | C5: =Assumptions!$B$6*(1+Assumptions!$B$7)^0 -> 68 | D5: =Assumptions!$B$6*(1+Assumptions!$B$7)^1 -> 71.06 | E5: =Assumptions!$B$6*(1+Assumptions!$B$7)^2 -> 74.2577 | F5: =Assumptions!$B$6*(1+Assumptions!$B$7)^3 -> 77.599296 | G5: =Assumptions!$B$6*(1+Assumptions!$B$7)^4 -> 81.091265 | H5: =Assumptions!$B$6*(1+Assumptions!$B$7)^5 -> 84.740372 | I5: =Assumptions!$B$6*(1+Assumptions!$B$7)^6 -> 88.553688 | J5: =Assumptions!$B$6*(1+Assumptions!$B$7)^7 -> 92.538604 | K5: =Assumptions!$B$6*(1+Assumptions!$B$7)^8 -> 96.702842 | L5: =Assumptions!$B$6*(1+Assumptions!$B$7)^9 -> 101.05447
A6: IIJA drawdown | B6: net drag x phasing | C6: =-Assumptions!$B$10*Assumptions!C$23 -> 0 | D6: =-Assumptions!$B$10*Assumptions!D$23 -> -1.005 | E6: =-Assumptions!$B$10*Assumptions!E$23 -> -2.68 | F6: =-Assumptions!$B$10*Assumptions!F$23 -> -5.025 | G6: =-Assumptions!$B$10*Assumptions!G$23 -> -6.7 | H6: =-Assumptions!$B$10*Assumptions!H$23 -> -6.7 | I6: =-Assumptions!$B$10*Assumptions!I$23 -> -6.7 | J6: =-Assumptions!$B$10*Assumptions!J$23 -> -6.7 | ... L6: =-Assumptions!$B$10*Assumptions!L$23 -> -6.7
A7: Lead service lines | B7: regulatory adder | C7: =Assumptions!C$24 -> 0 | D7: =Assumptions!D$24 -> 2 | E7: =Assumptions!E$24 -> 3.5 | F7: =Assumptions!F$24 -> 5 | G7: =Assumptions!G$24 -> 5.5 | H7: =Assumptions!H$24 -> 5.5 | I7: =Assumptions!I$24 -> 5 | J7: =Assumptions!J$24 -> 4.5 | ... L7: =Assumptions!L$24 -> 2
A8: PFAS | B8: regulatory adder | C8: =Assumptions!C$25 -> 0 | D8: =Assumptions!D$25 -> 1 | E8: =Assumptions!E$25 -> 1.8 | F8: =Assumptions!F$25 -> 2.5 | G8: =Assumptions!G$25 -> 2.5 | H8: =Assumptions!H$25 -> 2 | I8: =Assumptions!I$25 -> 1.5 | J8: =Assumptions!J$25 -> 1.2 | ... L8: =Assumptions!L$25 -> 1
A9: Total capital spending | B9: sum | C9: =SUM(C5:C8) -> 68 | D9: =SUM(D5:D8) -> 73.055 | E9: =SUM(E5:E8) -> 76.8777 | F9: =SUM(F5:F8) -> 80.074297 | G9: =SUM(G5:G8) -> 82.391265 | H9: =SUM(H5:H8) -> 85.540372 | I9: =SUM(I5:I8) -> 88.353688 | J9: =SUM(J5:J8) -> 91.538604 | ... L9: =SUM(L5:L8) -> 97.35447
A10: year on year | B10: growth | D10: =IF(C9=0,0,D9/C9-1) -> 0.074338235 | E10: =IF(D9=0,0,E9/D9-1) -> 0.052326329 | F10: =IF(E9=0,0,F9/E9-1) -> 0.041580283 | G10: =IF(F9=0,0,G9/F9-1) -> 0.028935232 | H10: =IF(G9=0,0,H9/G9-1) -> 0.038221369 | I10: =IF(H9=0,0,I9/H9-1) -> 0.03288876 | J10: =IF(I9=0,0,J9/I9-1) -> 0.036047346 | K10: =IF(J9=0,0,K9/J9-1) -> 0.032382373 | L10: =IF(K9=0,0,L9/K9-1) -> 0.030175049
A12: Summary
A13: Metric | B13: Value | D13: Note
A14: Cumulative spend 2027-2035 ($bn) | B14: =SUM(D9:L9) -> 769.68824 | D14: Base case. Sits between the escalated EPA survey floor and the ASCE/AWWA ceiling.
A15: CAGR 2026-2035 | B15: =(L9/C9)^(1/9)-1 -> 0.040677899 | D15: Mid-single-digit nominal. Not a boom, not a bust.
A16: Trough growth year | B16: =INDEX($C$4:$L$4,MATCH(MIN(D10:L10),D10:L10,0)+1) -> 2030 | D16: Where the federal drawdown concentrates.
A17: Trough growth rate | B17: =MIN(D10:L10) -> 0.028935232 | D17: Even at the worst point, growth stays positive.
A19: Reading: the federal drawdown costs roughly one to one and a half percentage points of market growth in the 2029-2030 window, and nothing thereafter. There is no credible scenario in which national water capital spending falls in nominal terms.

Sheet Scenarios
A1: Scenarios
A2: Bear / base / bull, each driven off its own row of levers on the Assumptions tab.
A4: Scenario | B4: Levers | C4: 2026 | D4: 2027 | E4: 2028 | F4: 2029 | G4: 2030 | H4: 2031 | I4: 2032 | J4: 2033 | K4: 2034 | L4: 2035
A5: Bear | B5: g / drag / adder | C5: =Assumptions!$B$6*(1+Assumptions!$B$15)^0-Assumptions!$C$15*Assumptions!C$23+Assumptions!$D$15*(Assumptions!C$24+Assumptions!C$25) -> 68 | D5: =Assumptions!$B$6*(1+Assumptions!$B$15)^1-Assumptions!$C$15*Assumptions!D$23+Assumptions!$D$15*(Assumptions!D$24+Assumptions!D$25) -> 70.19 | E5: =Assumptions!$B$6*(1+Assumptions!$B$15)^2-Assumptions!$C$15*Assumptions!E$23+Assumptions!$D$15*(Assumptions!E$24+Assumptions!E$25) -> 71.1912 | F5: =Assumptions!$B$6*(1+Assumptions!$B$15)^3-Assumptions!$C$15*Assumptions!F$23+Assumptions!$D$15*(Assumptions!F$24+Assumptions!F$25) -> 71.305436 | G5: =Assumptions!$B$6*(1+Assumptions!$B$15)^4-Assumptions!$C$15*Assumptions!G$23+Assumptions!$D$15*(Assumptions!G$24+Assumptions!G$25) -> 71.534599 | H5: =Assumptions!$B$6*(1+Assumptions!$B$15)^5-Assumptions!$C$15*Assumptions!H$23+Assumptions!$D$15*(Assumptions!H$24+Assumptions!H$25) -> 73.580637 | I5: =Assumptions!$B$6*(1+Assumptions!$B$15)^6-Assumptions!$C$15*Assumptions!I$23+Assumptions!$D$15*(Assumptions!I$24+Assumptions!I$25) -> 75.445556 | J5: =Assumptions!$B$6*(1+Assumptions!$B$15)^7-Assumptions!$C$15*Assumptions!J$23+Assumptions!$D$15*(Assumptions!J$24+Assumptions!J$25) -> 77.481423 | K5: =Assumptions!$B$6*(1+Assumptions!$B$15)^8-Assumptions!$C$15*Assumptions!K$23+Assumptions!$D$15*(Assumptions!K$24+Assumptions!K$25) -> 79.390366 | L5: =Assumptions!$B$6*(1+Assumptions!$B$15)^9-Assumptions!$C$15*Assumptions!L$23+Assumptions!$D$15*(Assumptions!L$24+Assumptions!L$25) -> 81.224577
A6: Base | B6: g / drag / adder | C6: =Assumptions!$B$6*(1+Assumptions!$B$16)^0-Assumptions!$C$16*Assumptions!C$23+Assumptions!$D$16*(Assumptions!C$24+Assumptions!C$25) -> 68 | D6: =Assumptions!$B$6*(1+Assumptions!$B$16)^1-Assumptions!$C$16*Assumptions!D$23+Assumptions!$D$16*(Assumptions!D$24+Assumptions!D$25) -> 73.055 | E6: =Assumptions!$B$6*(1+Assumptions!$B$16)^2-Assumptions!$C$16*Assumptions!E$23+Assumptions!$D$16*(Assumptions!E$24+Assumptions!E$25) -> 76.8777 | F6: =Assumptions!$B$6*(1+Assumptions!$B$16)^3-Assumptions!$C$16*Assumptions!F$23+Assumptions!$D$16*(Assumptions!F$24+Assumptions!F$25) -> 80.074297 | G6: =Assumptions!$B$6*(1+Assumptions!$B$16)^4-Assumptions!$C$16*Assumptions!G$23+Assumptions!$D$16*(Assumptions!G$24+Assumptions!G$25) -> 82.391265 | H6: =Assumptions!$B$6*(1+Assumptions!$B$16)^5-Assumptions!$C$16*Assumptions!H$23+Assumptions!$D$16*(Assumptions!H$24+Assumptions!H$25) -> 85.540372 | I6: =Assumptions!$B$6*(1+Assumptions!$B$16)^6-Assumptions!$C$16*Assumptions!I$23+Assumptions!$D$16*(Assumptions!I$24+Assumptions!I$25) -> 88.353688 | J6: =Assumptions!$B$6*(1+Assumptions!$B$16)^7-Assumptions!$C$16*Assumptions!J$23+Assumptions!$D$16*(Assumptions!J$24+Assumptions!J$25) -> 91.538604 | K6: =Assumptions!$B$6*(1+Assumptions!$B$16)^8-Assumptions!$C$16*Assumptions!K$23+Assumptions!$D$16*(Assumptions!K$24+Assumptions!K$25) -> 94.502842 | L6: =Assumptions!$B$6*(1+Assumptions!$B$16)^9-Assumptions!$C$16*Assumptions!L$23+Assumptions!$D$16*(Assumptions!L$24+Assumptions!L$25) -> 97.35447
A7: Bull | B7: g / drag / adder | C7: =Assumptions!$B$6*(1+Assumptions!$B$17)^0-Assumptions!$C$17*Assumptions!C$23+Assumptions!$D$17*(Assumptions!C$24+Assumptions!C$25) -> 68 | D7: =Assumptions!$B$6*(1+Assumptions!$B$17)^1-Assumptions!$C$17*Assumptions!D$23+Assumptions!$D$17*(Assumptions!D$24+Assumptions!D$25) -> 74.44 | E7: =Assumptions!$B$6*(1+Assumptions!$B$17)^2-Assumptions!$C$17*Assumptions!E$23+Assumptions!$D$17*(Assumptions!E$24+Assumptions!E$25) -> 79.9157 | F7: =Assumptions!$B$6*(1+Assumptions!$B$17)^3-Assumptions!$C$17*Assumptions!F$23+Assumptions!$D$17*(Assumptions!F$24+Assumptions!F$25) -> 85.098414 | G7: =Assumptions!$B$6*(1+Assumptions!$B$17)^4-Assumptions!$C$17*Assumptions!G$23+Assumptions!$D$17*(Assumptions!G$24+Assumptions!G$25) -> 89.040076 | H7: =Assumptions!$B$6*(1+Assumptions!$B$17)^5-Assumptions!$C$17*Assumptions!H$23+Assumptions!$D$17*(Assumptions!H$24+Assumptions!H$25) -> 93.12328 | I7: =Assumptions!$B$6*(1+Assumptions!$B$17)^6-Assumptions!$C$17*Assumptions!I$23+Assumptions!$D$17*(Assumptions!I$24+Assumptions!I$25) -> 96.911311 | J7: =Assumptions!$B$6*(1+Assumptions!$B$17)^7-Assumptions!$C$17*Assumptions!J$23+Assumptions!$D$17*(Assumptions!J$24+Assumptions!J$25) -> 101.18818 | K7: =Assumptions!$B$6*(1+Assumptions!$B$17)^8-Assumptions!$C$17*Assumptions!K$23+Assumptions!$D$17*(Assumptions!K$24+Assumptions!K$25) -> 105.30868 | L7: =Assumptions!$B$6*(1+Assumptions!$B$17)^9-Assumptions!$C$17*Assumptions!L$23+Assumptions!$D$17*(Assumptions!L$24+Assumptions!L$25) -> 109.39841
A9: Spread | B9: Basis | C9: 2026 | D9: 2027 | E9: 2028 | F9: 2029 | G9: 2030 | H9: 2031 | I9: 2032 | J9: 2033 | K9: 2034 | L9: 2035
A10: Bull less bear ($bn) | B10: range | C10: =C7-C5 -> 0 | D10: =D7-D5 -> 4.25 | E10: =E7-E5 -> 8.7245 | F10: =F7-F5 -> 13.792977 | G10: =G7-G5 -> 17.505477 | H10: =H7-H5 -> 19.542643 | I10: =I7-I5 -> 21.465755 | J10: =J7-J5 -> 23.70676 | ... L10: =L7-L5 -> 28.173834
A11: as % of bear | B11: range | C11: =C10/C5 -> 0 | D11: =D10/D5 -> 0.060549936 | E11: =E10/E5 -> 0.12255026 | F11: =F10/F5 -> 0.19343515 | G11: =G10/G5 -> 0.24471343 | H11: =H10/H5 -> 0.26559492 | I11: =I10/I5 -> 0.2845198 | J11: =J10/J5 -> 0.30596702 | ... L11: =L10/L5 -> 0.34686342
A13: Scenario endpoints
A14: Scenario | B14: 2030 ($bn) | C14: 2035 ($bn) | D14: CAGR 2026-35
A15: Bear | B15: =G5 -> 71.534599 | C15: =L5 -> 81.224577 | D15: =(L5/C5)^(1/9)-1 -> 0.019941807
A16: Base | B16: =G6 -> 82.391265 | C16: =L6 -> 97.35447 | D16: =(L6/C6)^(1/9)-1 -> 0.040677899
A17: Bull | B17: =G7 -> 89.040076 | C17: =L7 -> 109.39841 | D17: =(L7/C7)^(1/9)-1 -> 0.054252593
A19: The bear-to-bull spread by 2035 is the honest measure of confidence in this forecast. The direction, however, is up in every case — the disagreement is about pace, not sign.

Sheet Historical Spending
A1: Historical Spending
A2: Who actually pays for US water infrastructure.
A4: CBO — public spending on transportation and water infrastructure, 2023
A5: Metric | B5: Value | C5: Unit | D5: Share | E5: Source
A6: Total, all transportation and water infrastructure | B6: 626 | C6: $bn | E6: CBO, Public Spending on Transportation and Water Infrastructure 1956-2023, Feb 2025
A7: as % of GDP | B7: 0.023 | C7: % | E7: CBO
A8: Water utilities — total spending | B8: 175 | C8: $bn | D8: =B8/B6 -> 0.27955272 | E8: CBO via USAFacts. Water utilities take ~28% of the total.
A9: of which capital | B9: 59 | C9: $bn | D9: =B9/B8 -> 0.33714286 | E9: CBO. THIS IS THE ANCHOR FOR THE FORWARD MODEL BASE.
A10: of which operations and maintenance | B10: 114 | C10: $bn | D10: =B10/B8 -> 0.65142857 | E10: CBO. O&M is the majority — capital is the minority of utility spending.
A11: State and local share of water infrastructure | B11: 0.92 | C11: % | E11: CBO. Rises to ~96% on the narrower water supply and wastewater facilities definition.
A12: Federal share of water infrastructure | B12: 0.08 | C12: % | E12: CBO
A13: O&M as % of all public infrastructure spending | B13: 0.567 | C13: % | E13: CBO — $355bn of $625.8bn in 2023. Rising over time.
A14: State and local share of ALL public infrastructure | B14: 0.79 | C14: % | E14: CBO — $494.2bn of $625.8bn in 2023.
A16: Census Bureau — value of construction put in place (C30)
A17: Category | B17: Value | C17: Unit | D17: Basis | E17: Source and caveat
A18: Water supply — total construction | B18: 36.5 | C18: $bn | D18: SAAR Jan-2026 | E18: Census C30. Includes private work.
A19: Water supply — public construction | B19: 34.8 | C19: $bn | D19: SAAR Jan-2026 | E19: Census C30 / FRED PBWSCONS
A20: Sewage and waste disposal — total | B20: 54.3 | C20: $bn | D20: SAAR Jan-2026 | E20: Census C30. CAUTION: bundles SOLID WASTE facilities with sewerage — overstates wastewater.
A21: Sewage and waste disposal — public | B21: 53 | C21: $bn | D21: SAAR Jan-2026 | E21: Census C30
A22: Naive sum (both categories, total construction) | B22: =B18+B20 -> 90.8 | C22: $bn | D22: formula | E22: This is the $88bn figure an earlier draft used as the capital base. It is NOT water capital spending — see the reconciliation on the Needs Estimates tab.
A24: Longer-run local capital spending
A25: Metric | B25: Value | C25: Unit | D25: Period | E25: Source
A26: Local capital spending — sewer, cumulative | B26: 350 | C26: $bn | D26: 2012-2024 | E26: US Conference of Mayors, 2025 Public Infrastructure Spending
A27: annual average | B27: =B26/13 -> 26.923077 | C27: $bn | D27: formula | E27: Local government only
A28: Local capital spending — water supply, cumulative | B28: 226 | C28: $bn | D28: 2012-2024 | E28: US Conference of Mayors
A29: annual average | B29: =B28/13 -> 17.384615 | C29: $bn | D29: formula | E29: Local government only
A30: All public community-asset capital spending, 2012 | B30: 279 | C30: $bn | D30: 2012 | E30: US Conference of Mayors
A31: All public community-asset capital spending, 2024 | B31: 492 | C31: $bn | D31: 2024 | E31: US Conference of Mayors
A32: growth 2012-2024 | B32: =B31/B30-1 -> 0.76344086 | C32: % | D32: formula | E32: +76%
A34: The real funding engine — rates, debt and water loss
A35: Metric | B35: Value | C35: Unit | D35: Period | E35: Source
A36: Water and sewer bill increase | B36: 0.051 | C36: % | D36: 2025 | E36: Bluefield Research, US Municipal Water & Sewer Rate Index (50 cities)
A37: cumulative five-year increase | B37: 0.242 | C37: % | D37: 2020-2025 | E37: Bluefield Research
A38: water rates | B38: 0.06 | C38: % | D38: 2024-25 | E38: Bluefield Research
A39: wastewater rates | B39: 0.048 | C39: % | D39: 2024-25 | E39: Bluefield Research
A40: Water and sewer bond issuance | B40: 27.9 | C40: $bn | D40: 2010 low | E40: Historical reference range
A41: upper end of range | B41: 39.9 | C41: $bn | D41: 2013 high | E41: Historical reference range
A42: Non-revenue water — share of treated supply | B42: 0.195 | C42: % | D42: current | E42: Bluefield Research
A43: volume lost daily | B43: 6.75 | C43: bn gallons/day | D43: current | E43: Bluefield Research
A44: lost revenue | B44: 6.4 | C44: $bn p.a. | D44: current | E44: Bluefield Research
A46: A single year of national rate increases generates more incremental utility spending capacity than the entire annual IIJA water supplemental. This is the variable that matters most for distributor revenue, and it is the one least discussed.

Sheet Federal Programs
A1: Federal Programs
A2: Four federal channels. Only one is large, and it expires 30 September 2026.
A4: State Revolving Funds — appropriations
A5: Item | B5: Value | C5: Unit | D5: Period | E5: Source
A6: Total annual SRF funding, pre-IIJA | B6: 2.7 | C6: $bn | D6: FY2021 | E6: National League of Cities
A7: Total annual SRF funding, with IIJA | B7: 11.4 | C7: $bn | D7: FY2022-26 avg | E7: National League of Cities — a ~4x step up
A8: Clean Water SRF — total available | B8: 1.64 | C8: $bn | D8: FY2021 | E8: CRS
A9: Clean Water SRF — regular appropriation | B9: 1.6 | C9: $bn | D9: FY2025 | E9: CRS
A10: Clean Water SRF — IIJA supplemental | B10: 2.6 | C10: $bn | D10: FY2025 | E10: CRS
A11: Drinking Water SRF — regular appropriation | B11: 1.1 | C11: $bn | D11: FY2025 | E11: CRS
A12: Drinking Water SRF — IIJA supplemental | B12: 2.6 | C12: $bn | D12: FY2025 | E12: CRS
A13: EPA water infrastructure programs — total | B13: 3.04 | C13: $bn | D13: FY2026 | E13: P.L. 119-74, same as FY2025 enacted (P.L. 119-4)
A14: Regular appropriations for EPA water infrastructure programs have been FLAT across FY2024, FY2025 and FY2026. All growth in the period came from the IIJA supplemental.
A17: IIJA / Bipartisan Infrastructure Law supplemental — expiring
A18: Pot | B18: Amount | C18: Unit | D18: Period | E18: Note
A19: Clean Water SRF general supplemental | B19: 11.7 | C19: $bn | D19: FY2022-26 | E19: Predominantly loans
A20: Drinking Water SRF general supplemental | B20: 11.7 | C20: $bn | D20: FY2022-26 | E20: Predominantly loans
A21: DWSRF — lead service line replacement | B21: 15 | C21: $bn | D21: FY2022-26 | E21: High principal-forgiveness requirement
A22: DWSRF — emerging contaminants (PFAS) | B22: 4 | C22: $bn | D22: FY2022-26 | E22: Grant-like for disadvantaged communities
A23: Other pots (CWSRF emerging contaminants etc.) | B23: 7.6 | C23: $bn | D23: FY2022-26 | E23: Balance to the >$50bn headline
A24: Total IIJA water supplemental | B24: =SUM(B19:B23) -> 50 | C24: $bn | D24: FY2022-26 | E24: EPA states 'over $50 billion'. Expires 30 September 2026.
A26: The cliff arithmetic
A27: Step | B27: Value | C27: Unit | E27: Reasoning
A28: 1. Gross federal step-down | B28: =Assumptions!B8 -> 8.7 | C28: $bn p.a. | E28: $11.4bn (FY22-26) less $2.7bn (FY21)
A29: as % of the 2026 capital base | B29: =B28/Assumptions!B6 -> 0.12794118 | C29: % | E29: Formula
A30: 2. Share not yet at municipality level | B30: 0.67 | C30: % | E30: Core & Main, Q1 FY2026 call: 'only about a third or less of it has hit the municipality level yet'
A31: dollars still to disburse | B31: =B30*B24 -> 33.5 | C31: $bn | E31: Spreads the drawdown across 2027-2030 rather than at expiry
A32: 3. Permanent revolving offset | B32: =Assumptions!B9 -> 2 | C32: $bn p.a. | E32: ESTIMATE. ~50/50 grant vs loan split; loans recycle into the state corpus
A33: 4. Net steady-state drag | B33: =Assumptions!B10 -> 6.7 | C33: $bn p.a. | E33: Formula
A34: as % of the 2026 capital base | B34: =Assumptions!B11 -> 0.098529412 | C34: % | E34: The honest measure of the cliff — not the 100% often assumed
A36: WIFIA, earmarks and reauthorisation
A37: Item | B37: Value | C37: Unit | D37: As at | E37: Note
A38: WIFIA — cumulative financing closed | B38: 23 | C38: $bn | D38: May 2026 | E38: 152 closed loans
A39: WIFIA — total project value supported | B39: 51 | C39: $bn | D39: May 2026 | E39: Leverage, not subsidy
A40: WIFIA — capacity still available | B40: 11 | C40: $bn | D40: 2026 | E40: EPA waiving fees for small communities
A41: WIFIA — FY2025 closings | B41: 1.2 | C41: $bn | D41: FY2025 | E41: 8 loans
A42: WIFIA — 2026 year-to-date closings | B42: 0.682 | C42: $bn | D42: early 2026 | E42: 3 loans
A43: FY2027 House bill — proposed SRF cut | B43: -0.16 | C43: % | D43: FY2027 | E43: Committee markup, June 2026
A44: FY2027 DWSRF proposed level | B44: 0.91 | C44: $bn | D44: FY2027 | E44: Down from $1.126bn in FY2026
A45: FY2027 earmarks — water projects | B45: 1 | C45: $bn | D45: FY2027 | E45: ~1,200 projects, carved OUT of SRF not added to it
A46: WRDA 2026 — CWSRF authorisation | B46: 14 | C46: $bn | D46: over 4 yrs | E46: Senate EPW text, 13 July 2026. AUTHORISATION, not appropriation.
A47: WRDA 2026 — DWSRF authorisation | B47: 16.5 | C47: $bn | D47: over 5 yrs | E47: $3.3bn/yr — triple current appropriations but BELOW the FY22-26 run-rate
A48: WRDA 2026 — WIFIA authorisation | B48: 0.065 | C48: $bn p.a. | D48: through FY2030 | E48: Senate EPW

Sheet Needs Estimates
A1: Needs Estimates and the Capital Base
A2: The four published studies disagree by 3x because they measure different things.
A4: Study | B4: Headline | C4: Unit | D4: Annualised ($bn) | E4: What it measures / whose interest
A5: EPA 7th DWINSA (Sep 2023) | B5: 625 | C5: $bn / 20yr | D5: =B5/20 -> 31.25 | E5: SRF-ELIGIBLE drinking water projects, self-reported by states. Jan-2021 dollars; $648.8bn in 2022 dollars per CRS. Allocation instrument — states self-report into their own funding formula.
A6: EPA CWNS 2022 (Apr 2024) | B6: 630.1 | C6: $bn / 20yr | D6: =B6/20 -> 31.505 | E6: SRF-ELIGIBLE clean water needs with documentation. +73% vs 2012, but first survey with 100% state participation — which mechanically inflates the increase.
A7: ASCE Bridging the Gap (2024) | B7: 99 | C7: $bn/yr gap | D7: =B7+Assumptions!B6 -> 167 | E7: Annualised column = gap + actual spend. Full economic need incl. resilience and growth, from the civil engineers' professional society. Up from $81bn in 2021. NOTE: ASCE separately reports wastewater+stormwater annual capital NEEDS of $99bn with a $69bn gap — the same headline number used two different ways. Route 3 of the base reconciliation uses the latter.
A8: AWWA Beyond the Replacement Era (Mar 2026) | B8: 2250 | C8: $bn / 25yr | D8: =B8/25 -> 90 | E8: Drinking water ONLY. Replacement + PFAS + lead + climate + cyber + O&M. Midpoint of $2.1-2.4tn (2025 dollars). Utility trade association; requires a 168% increase in annual capital investment.
A10: EPA surveys — combined and escalated
A11: Step | B11: Value | C11: Unit | E11: Basis
A12: Combined annualised eligible need | B12: =D5+D6 -> 62.755 | C12: $bn/yr | E12: 2021/2022 dollars, un-escalated
A13: Construction cost escalation | B13: 0.045 | C13: % p.a. | E13: Assumed
A14: Years to escalate | B14: 4.5 | C14: yrs | E14: Mid-2021/22 base to 2026
A15: Escalated eligible need, 2026 dollars | B15: =B12*(1+B13)^B14 -> 76.501798 | C15: $bn/yr | E15: Formula
A17: Reconciling the capital base — four independent routes to the same number
A18: Route | B18: Value | C18: Unit | E18: Derivation
A19: 1. CBO water utilities capital, 2023 | B19: 59 | C19: $bn | E19: CBO. Public sector, water supply and wastewater.
A20: escalated to 2026 at 4.5% p.a. | B20: =B19*(1+B13)^3 -> 67.328801 | C20: $bn | E20: Formula
A21: 2. Census water supply (total construction) | B21: 36.5 | C21: $bn | E21: Census C30, SAAR Jan-2026
A22: Census sewage and waste disposal | B22: 54.3 | C22: $bn | E22: Census C30, SAAR Jan-2026
A23: assumed sewerage share of that category | B23: 0.65 | C23: % | E23: ESTIMATE. The rest is solid waste disposal — landfill, waste-to-energy.
A24: adjusted total, public share (95%) | B24: =(B21+B22*B23)*0.95 -> 68.20525 | C24: $bn | E24: Formula
A25: 3. ASCE implied wastewater + stormwater actual | B25: 30 | C25: $bn | E25: ASCE: annual capital needs $99bn, gap $69bn, so ~30% of needs met.
A26: 4. AWWA implied drinking water actual | B26: =D8/2.68 -> 33.58209 | C26: $bn | E26: AWWA requires a 168% increase to reach its target, so current spend is target / 2.68.
A27: routes 3 + 4 combined | B27: =B25+B26 -> 63.58209 | C27: $bn | E27: Formula
A28: Average of routes 1 and 2 (primary) | B28: =AVERAGE(B20,B24) -> 67.767026 | C28: $bn | E28: The two strongest routes: a non-partisan scorekeeper and official construction statistics.
A29: Average of all three routes | B29: =AVERAGE(B20,B24,B27) -> 66.372047 | C29: $bn | E29: Routes 3 and 4 are weaker — both read advocacy claims backwards — and pull the average down.
A30: Implied range | B30: =MIN(B20,B24,B27) -> 63.58209 | C30: $bn | D30: =MAX(B20,B24,B27) -> 68.20525 | E30: Low to high across the three routes.
A31: ADOPTED BASE | B31: =Assumptions!B6 -> 68 | C31: $bn | E31: Rounded to $68bn — the midpoint of the two primary routes. Sits at the upper end of the three-route range because routes 3 and 4 are derived from advocacy studies read in reverse and are the least reliable. Change it on the Assumptions tab to test the low end.
A32: variance vs three-route average | B32: =Assumptions!B6/B29-1 -> 0.02452769 | C32: % | E32: Formula. The model is ~2.5% above the most conservative reading of the base.
A33: Gap: escalated need less actual spend | B33: =B15-Assumptions!B6 -> 8.5017977 | C33: $bn/yr | E33: The documented, SRF-eligible shortfall — an order of magnitude below the ASCE headline.
A34: as % of actual spend | B34: =B33/Assumptions!B6 -> 0.12502644 | C34: % | E34: Formula
A36: WHY THE FOUR STUDIES DIVERGE. The EPA surveys are floors by construction: they count only what states could document as eligible, and assume a 0.5%/yr pipe replacement rate — which imputes a 200-YEAR pipe life against an observed 53-year average failure age. The ASCE and AWWA figures are ceilings by construction, produced by parties that advocate for higher appropriations. The truth is bracketed, not split.
A38: Market-research forecasts (the view that maps to distributor revenue)
A39: Forecast | B39: Value | C39: Unit | D39: Period | E39: Source
A40: US municipal water + wastewater treatment capex | B40: 515.4 | C40: $bn | D40: through 2035 | E40: Bluefield Research — 4.4% CAGR
A41: starting annual rate | B41: 37.2 | C41: $bn | D41: 2026 | E41: Bluefield Research
A42: ending annual rate | B42: 57.3 | C42: $bn | D42: 2035 | E42: Bluefield Research
A43: of which wastewater | B43: 310.4 | C43: $bn | D43: through 2035 | E43: Bluefield Research — 58% of total
A44: of which upgrades / rehab of existing assets | B44: 406.4 | C44: $bn | D44: through 2035 | E44: Bluefield Research — 79%. The replacement thesis, quantified.
A45: US + Canada municipal pipe capex | B45: 99.3 | C45: $bn | D45: 2026-2035 | E45: Bluefield Research — ~$10bn/yr

Sheet Pipe and Assets
A1: Pipe and Assets — the Engineering Evidence
A2: Utah State University, Water Main Break Rates in the USA and Canada, Dec 2023.
A4: Study scope
A5: Metric | B5: Value | C5: Unit | F5: Note
A6: Utilities surveyed | B6: 802 | C6: count | F6: 49 US states and all 10 Canadian provinces
A7: Population served by respondents | B7: 0.3 | C7: % | F7: >30% of the US and Canada population
A8: Miles of main represented | B8: 400000 | C8: miles | F8: >17% of the estimated 2.3m miles in both countries
A9: Publication date | B9: 2023 | C9: year | F9: Released Feb 2024 by USU's Utah Water Research Laboratory
A10: BIAS NOTE: the study is academic but distributed by pipe-manufacturer interests, and its material-by-material results favour PVC. It is also the best dataset available — and its finding that break rates FELL cuts against its own $452bn funding-gap headline.
A13: Break rates and material mix
A14: Material | B14: Breaks per 100 mi/yr | C14: Miles surveyed | D14: % of surveyed miles | E14: % over 50 yrs old | F14: Failure mechanism
A15: Cast iron | B15: 28.6 | C15: 90657 | D15: =C15/$C$20 -> 0.24542021 | E15: 0.86 | F15: Graphitic corrosion — iron matrix leaches away leaving a graphite skeleton that holds shape and pressure until it fails without warning. Plus tuberculation.
A16: Asbestos cement | B16: 10.3 | C16: 42365 | D16: =C16/$C$20 -> 0.11468753 | E16: 0.41 | F16: Cement matrix leaches from both faces; progressive wall-strength loss. Handling, worker-safety and disposal premiums on replacement.
A17: Steel | B17: 9.2 | C17: 11358 | D17: =C17/$C$20 -> 0.030747574 | F17: External and internal corrosion; joint and weld failure.
A18: Ductile iron | B18: 5.1 | C18: 108670 | D18: =C18/$C$20 -> 0.29418373 | F18: Corrosion where unprotected; polyethylene encasement materially extends life.
A19: PVC | B19: 2.9 | C19: 116345 | D19: =C19/$C$20 -> 0.31496095 | F19: Low failure rate; failures typically installation-related or from impact/third-party damage.
A20: Total surveyed | C20: =SUM(C15:C19) -> 369395 | D20: =SUM(D15:D19) -> 1 | F20: Formula
A21: National average break rate | B21: 11.1 | F21: Down from 14.0 in the 2018 study — a ~20% decline in five years.
A22: 2018 study national average | B22: 14 | F22: USU 2018
A23: Change 2018 to 2023 | B23: =B21/B22-1 -> -0.20714286 | F23: THE COUNTER-EVIDENCE: the network is measurably getting MORE reliable, not less.
A24: Cast iron vs PVC failure ratio | B24: =B15/B19 -> 9.862069 | F24: The single most defensible number in the replacement case.
A26: Asset inventory and condition
A27: Metric | B27: Value | C27: Unit | F27: Source
A28: Drinking water transmission and distribution mains | B28: 2200000 | C28: miles | F28: EPA / ASCE
A29: Community water systems | B29: 50000 | C29: count | F29: EPA — of 148,000+ public water systems total
A30: Public sewers | B30: 800000 | C30: miles | F30: ASCE — plus ~500,000 miles of private laterals
A31: Publicly owned treatment works | B31: 17544 | C31: count | F31: EPA CWNS 2022 — serving 270.4m people, 82% of population
A32: POTW average utilisation of design capacity | B32: 0.81 | C32: % | F32: ASCE
A33: POTWs at or over design capacity | B33: 0.15 | C33: % | F33: ASCE
A34: Water mains over 50 years old | B34: 0.33 | C34: % | F34: USU 2023 — approximately 770,000 miles
A35: Water mains beyond useful life | B35: 0.194 | C35: % | F35: USU 2023 — approximately 452,000 miles
A36: Average age of failing water main | B36: 53 | C36: years | F36: USU 2023
A37: Estimated cost to replace aging mains | B37: 452 | C37: $bn | F37: USU 2023, US and Canada
A38: Water main breaks per year | B38: 260000 | C38: count | F38: USU 2023, US and Canada — one every two minutes
A39: Annual repair cost of those breaks | B39: 2.6 | C39: $bn | F39: USU 2023
... A41: Untreated CSO discharge | B41: 850 | C41: bn gallons/yr | F41: EPA
A42: Implied average cost per break | B42: =B39*1000000000/B38 -> 10000 | C42: $ | F42: Formula. Direct repair cost only — excludes boil-water notices, road closure and third-party damage.
A44: Demand — the evidence against capacity expansion
A45: Metric | B45: Value | C45: Unit | D45: Period | F45: Source
A46: Per capita withdrawal, 2000 | B46: 140 | C46: gal/capita/day | D46: 2000 | F46: USGS
A47: Per capita withdrawal, 2020 | B47: 127 | C47: gal/capita/day | D47: 2020 | F47: USGS
A48: Public-supply domestic per capita, 2010 | B48: 88 | C48: gal/day | D48: 2010 | F48: USGS
A49: Public-supply domestic per capita, 2015 | B49: 82 | C49: gal/day | D49: 2015 | F49: USGS
A50: Total US withdrawals, 2015 | B50: 322 | C50: bn gal/day | D50: 2015 | F50: USGS — down 9% from 2010
A51: Public-supply withdrawals fell even as population grew 4%. The sector's spending need is almost entirely RENEWAL, not expansion — which means capacity-expansion arguments outside data-centre and Sun Belt growth corridors are weak, and some existing infrastructure is oversized for current demand.

Sheet Regulatory
A1: Regulatory Drivers
A2: Legally dated obligations — the highest-conviction component of the forecast.
A4: Lead and Copper Rule Improvements
A5: Item | B5: Value | C5: Unit | D5: Date / status | E5: Note
A6: National lead service lines | B6: 9200000 | C6: count | D6: EPA 7th DWINSA | E6: First-ever national count.
A7: EPA cost per line — low | B7: 4700 | C7: $ | D7: EPA | E7: Utilities dispute as too low.
A8: EPA cost per line — high | B8: 6930 | C8: $ | D8: EPA | E8: New York estimates up to $11,000.
A9: Implied national cost — low | B9: =B6*B7/1000000000 -> 43.24 | C9: $bn | D9: formula | E9: Consensus estimates cluster at $45-60bn.
A10: Implied national cost — high | B10: =B6*B8/1000000000 -> 63.756 | C10: $bn | D10: formula
A11: Dedicated IIJA funding | B11: 15 | C11: $bn | D11: FY2022-26 | E11: Covers roughly a quarter to a third.
A12: Unfunded balance (midpoint) | B12: =AVERAGE(B9:B10)-B11 -> 38.498 | C12: $bn | D12: formula | E12: Must come from rates. This is the rate-driver, not the grant story.
A13: Baseline inventory / plan deadline | D13: 1 November 2027 | E13: Inventory, replacement plan, school and childcare list, updated sampling plan.
A14: Full replacement deadline | D14: 2034-2037 | E14: Ten years from compliance date, REGARDLESS of measured lead levels.
A15: Litigation | D15: Oral argument expected Fall 2026 | E15: AWWA v. EPA — challenges mandated replacement of lines 'under the control' of the utility. THE LARGEST BINARY RISK IN THIS FORECAST.
A17: PFAS
A18: Item | B18: Value | C18: Unit | D18: Date / status | E18: Note
A19: PFOA / PFOS maximum contaminant level | B19: 4 | C19: ppt | D19: RETAINED | E19: EPA proposal of 18 May 2026 upholds these.
A20: Original compliance deadline | D20: 26 April 2029 | E20: 2024 final rule.
A21: Proposed extended deadline | D21: 26 April 2031 | E21: On request, not automatic — EPA declined an automatic extension.
A22: PFHxS, PFNA, GenX, Hazard Index MCLs | D22: PROPOSED FOR RESCISSION | E22: On legal and procedural grounds under the SDWA, NOT on the health science.
A23: Comment period | D23: Closed 20 July 2026 | E23: Public hearing held 7 July 2026.
A24: Sector treatment cost | B24: 50 | C24: $bn / 20yr | D24: AWWA / Black & Veatch | E24: Trade-association model produced to argue against a stricter rule.
A25: CERCLA disposal cost if designated | B25: 3.5 | C25: $bn p.a. | D25: potential | E25: Residuals disposal exposure.
A26: Household rate impact — low | B26: 305 | C26: $ p.a. | D26: AWWA
A27: Household rate impact — high | B27: 3570 | C27: $ p.a. | D27: AWWA | E27: Worst for small systems, where fewer households share the cost.
A28: NET EFFECT of the 2026 proposals: the PFAS opportunity is SMALLER and LATER than the 2024 rule implied. Retaining only PFOA and PFOS reduces the number of systems triggered, and slipping compliance two years pushes capital into 2029-2031. Any model built on the full six-compound rule is stale.
A31: Other regulatory drivers
A32: Driver | B32: Scale | C32: Unit | D32: Mechanism | E32: Note
A33: CSO / SSO consent decrees | B33: 860 | C33: communities | D33: Court-supervised Clean Water Act settlements | E33: A court order is not a budget line — non-deferrable, multi-decade.
A34: Untreated CSO discharge | B34: 850 | C34: bn gal/yr | D34: EPA | E34: Concentrated in older Northeast, Great Lakes and Pacific Northwest cities.
A35: POTW end-of-life | B35: 40 | C35: yr design life | D35: 1972 Clean Water Act cohort | E35: Equipment life 15-20 years; plants 40-50.
A36: Data centre water consumption today | B36: 18 | C36: bn gal/yr | D36: New demand | E36: Midpoint of 17-19bn.
A37: Data centre water consumption 2030 | B37: 85 | C37: bn gal/yr | D37: New demand | E37: Midpoint of 60-110bn. 97% supplied by municipal systems.

Sheet Core and Main
A1: Core & Main (CNM)
A2: Fiscal years end the Sunday nearest 31 January and are labelled by end date. $m unless stated. Data sourced from Quartr.
A4: Income statement — five years
A5: $m | B5: FY end Jan-2022 | C5: FY end Jan-2023 | D5: FY end Jan-2024 | E5: FY end Feb-2025 | F5: FY end Feb-2026 | G5: Note
A6: Net sales | B6: 5004 | C6: 6651 | D6: 6702 | E6: 7441 | F6: 7647 | G6: Quartr — standardised income statement
A7: growth | C7: =C6/B6-1 -> 0.32913669 | D7: =D6/C6-1 -> 0.0076680198 | E7: =E6/D6-1 -> 0.11026559 | F7: =F6/E6-1 -> 0.027684451 | G7: Formula
A8: Gross profit | B8: 1280 | C8: 1795 | D8: 1818 | E8: 1980 | F8: 2059 | G8: Quartr
A9: gross margin | B9: =B8/B6 -> 0.25579536 | C9: =C8/C6 -> 0.26988423 | D9: =D8/D6 -> 0.27126231 | E9: =E8/E6 -> 0.26609327 | F9: =F8/F6 -> 0.26925592 | G9: Formula
A10: EBITDA (standardised) | B10: 604 | C10: 918 | D10: 889 | E10: 905 | F10: 913 | G10: Quartr. Company-reported Adjusted EBITDA for FY end Feb-2026 was $931m.
A11: EBITDA margin | B11: =B10/B6 -> 0.12070344 | C11: =C10/C6 -> 0.13802436 | D11: =D10/D6 -> 0.13264697 | E11: =E10/E6 -> 0.12162344 | F11: =F10/F6 -> 0.11939323 | G11: Formula
A12: Operating income | B12: 425 | C12: 775 | D12: 740 | E12: 719 | F12: 722 | G12: Quartr
A13: Net income | B13: 225 | C13: 366 | D13: 371 | E13: 434 | F13: 462 | G13: Quartr
A14: Diluted EPS ($) | B14: 0.55 | C14: 2.13 | D14: 2.15 | E14: 2.13 | F14: 2.31 | G14: Quartr
A15: Revenue CAGR, FY22 to FY26 | B15: =(F6/B6)^(1/4)-1 -> 0.11184295 | G15: Formula. Includes the 2021-22 inflation surge.
A17: End-market and product mix — fiscal year ended 1 February 2026
A18: Segment | B18: % of net sales | C18: Implied $m | G18: Source
A19: Municipal | B19: 0.44 | C19: =B19*$F$6 -> 3364.68 | G19: Core & Main Q1 FY2026 investor presentation, slide 12
A20: Non-residential | B20: 0.38 | C20: =B20*$F$6 -> 2905.86 | G20: Core & Main Q1 FY2026 investor presentation, slide 12
A21: Residential | B21: 0.18 | C21: =B21*$F$6 -> 1376.46 | G21: Core & Main Q1 FY2026 investor presentation, slide 12
A22: Total | B22: =SUM(B19:B21) -> 1 | C22: =SUM(C19:C21) -> 7647 | G22: Formula
A24: Split | B24: Share | G24: Source
A25: New construction | B25: 0.5 | G25: Core & Main Q1 FY2026 deck
A26: Repair and replace | B26: 0.5 | G26: The least cyclical revenue in the sector — funded from rates and O&M
A28: Market position and scale
A29: Metric | B29: Value | C29: Unit | G29: Source
A30: US total addressable market | B30: 39 | C30: $bn | G30: Core & Main deck, based on third-party research
A31: US market share | B31: 0.2 | C31: % | G31: Core & Main deck
A32: US + Canada TAM | B32: 44 | C32: $bn | G32: Core & Main deck
A33: US + Canada market share | B33: 0.17 | C33: % | G33: Core & Main deck
A34: Branches | B34: 370 | C34: count | G34: As at 3 May 2026
A35: Associates | B35: 5600 | C35: count | G35: As at 3 May 2026
A36: Customers | B36: 60000 | C36: count | G36: As at 3 May 2026
A37: Products | B37: 225000 | C37: count | G37: As at 3 May 2026
A38: Cross-check: TAM x share | B38: =B30*B31*1000 -> 7800 | C38: $m | G38: Formula. Compare with reported net sales of $7,647m — internally consistent.
A40: Q1 fiscal 2026 (quarter ended 3 May 2026) and guidance
A41: Metric | B41: Q1 FY26 | C41: Q1 FY25 | D41: Change | G41: Note
A42: Net sales ($m) | B42: 1911 | C42: 1910 | D42: =B42/C42-1 -> 0.00052356021 | G42: Core & Main Q1 FY2026 deck
A43: Gross profit ($m) | B43: 520 | C43: 510 | D43: =B43/C43-1 -> 0.019607843 | G43: Core & Main Q1 FY2026 deck
A44: Adjusted EBITDA ($m) | B44: 226 | C44: 224 | D44: =B44/C44-1 -> 0.0089285714 | G44: Core & Main Q1 FY2026 deck
A45: Net income ($m) | B45: 113 | C45: 105 | D45: =B45/C45-1 -> 0.076190476 | G45: Core & Main Q1 FY2026 deck
A46: Gross margin | B46: 0.272 | C46: 0.267 | D46: =B46-C46 -> 0.005 | G46: +50bps
A47: Adjusted diluted EPS ($) | B47: 0.72 | C47: 0.68 | D47: =B47/C47-1 -> 0.058823529 | G47: +6%
A49: FY2026 guidance | B49: Low | C49: High | D49: vs FY2025 | G49: Note
A50: Net sales ($m) | B50: 7800 | C50: 7900 | D50: =AVERAGE(B50:C50)/$F$6-1 -> 0.026546358 | G50: Reaffirmed at Q1. Growth of 2-3%.
A51: Adjusted EBITDA ($m) | B51: 950 | C51: 980 | G51: FY2025 adjusted EBITDA was $931m
A52: Adjusted EBITDA margin | B52: 0.122 | C52: 0.124 | G52: FY2025 margin 12.2%
A54: Above-market growth initiatives
A55: Initiative | B55: 5-yr sales CAGR | C55: Size | G55: Driver
A56: Treatment plant solutions | B56: 15-25% | C56: mid-single-digit % of net sales | G56: Aging facilities plus regulatory requirements; management: 'supported by durable funding' and 'non-discretionary'
A57: Smart utility / AMI metering | B57: 15-25% | C57: not disclosed; growing double digits | G57: Multi-year municipal AMI programmes; non-revenue water economics
A58: The deck reports 15% and 25% five-year CAGRs for the two initiatives; the pairing is ambiguous in the source layout, so both are shown as a range rather than assigned. Management confirmed treatment plant is mid-single-digit % of sales and growing double digits.

Sheet Ferguson
A1: Ferguson Enterprises (FERG)
A2: Fiscal years ended 31 July through FY2025; the company then moved to a 31 December year end. $m. Data sourced from Quartr.
A4: Income statement — eight periods
A5: $m | B5: FY Jul-19 | C5: FY Jul-20 | D5: FY Jul-21 | E5: FY Jul-22 | F5: FY Jul-23 | G5: FY Jul-24 | H5: FY Jul-25 | I5: CY Dec-25 | J5: Note
A6: Net sales | B6: 22010 | C6: 21819 | D6: 22792 | E6: 28566 | F6: 29734 | G6: 29635 | H6: 30762 | I6: 31316 | J6: CY Dec-25 is a transition period, not comparable to the July years
A7: growth | C7: =C6/B6-1 -> -0.0086778737 | D7: =D6/C6-1 -> 0.044594161 | E7: =E6/D6-1 -> 0.2533345 | F7: =F6/E6-1 -> 0.040887769 | G7: =G6/F6-1 -> -0.0033295218 | H7: =H6/G6-1 -> 0.038029357 | I7: =I6/H6-1 -> 0.018009232 | J7: Formula
A8: Gross profit | B8: 6458 | C8: 6421 | D8: 6980 | E8: 8756 | F8: 9025 | G8: 9053 | H8: 9435 | I8: 9708 | J8: Quartr
A9: gross margin | B9: =B8/B6 -> 0.29341209 | C9: =C8/C6 -> 0.2942848 | D9: =D8/D6 -> 0.30624781 | E9: =E8/E6 -> 0.30651824 | F9: =F8/F6 -> 0.30352458 | G9: =G8/G6 -> 0.30548338 | H9: =H8/H6 -> 0.30670958 | I9: =I8/I6 -> 0.31000128 | J9: Formula
A10: EBITDA | C10: 1581 | D10: 2168 | E10: 3121 | F10: 2980 | G10: 2987 | H10: 2979 | I10: 3243 | J10: Quartr; FY Jul-19 not available
A11: Operating income | B11: 1402 | C11: 1422 | D11: 2034 | E11: 2820 | F11: 2659 | G11: 2652 | H11: 2606 | I11: 2789 | J11: Quartr
A12: operating margin | B12: =B11/B6 -> 0.063698319 | C12: =C11/C6 -> 0.065172556 | D12: =D11/D6 -> 0.089241839 | E12: =E11/E6 -> 0.098718757 | F12: =F11/F6 -> 0.089426246 | G12: =G11/G6 -> 0.08948878 | H12: =H11/H6 -> 0.084714908 | I12: =I11/I6 -> 0.089059905 | J12: Formula
A13: Net income | B13: 1108 | C13: 961 | D13: 1508 | E13: 2122 | F13: 1889 | G13: 1735 | H13: 1856 | I13: 2006 | J13: Quartr
A15: US net sales by customer group — quarter ended 30 June 2026
A16: Customer group | B16: % of US sales | C16: Growth Q2 CY26 | D16: Growth Q2 CY25 | E16: Implied $m/qtr | J16: Source
A17: Waterworks | B17: 0.24 | C17: 0.03 | D17: 0.15 | E17: =B17*$E$25 -> 2002.32 | J17: Ferguson Q2 CY2026 deck, slide 7
A18: Ferguson Home | B18: 0.2 | C18: -0.01 | D18: 0.02 | E18: =B18*$E$25 -> 1668.6 | J18: Ferguson Q2 CY2026 deck, slide 7
A19: Commercial / Mechanical | B19: 0.16 | C19: 0.15 | D19: 0.2 | E19: =B19*$E$25 -> 1334.88 | J19: Ferguson Q2 CY2026 deck, slide 7
A20: Residential Trade Plumbing | B20: 0.14 | C20: 0 | D20: -0.02 | E20: =B20*$E$25 -> 1168.02 | J20: Ferguson Q2 CY2026 deck, slide 7
A21: HVAC | B21: 0.13 | C21: 0.11 | D21: 0.01 | E21: =B21*$E$25 -> 1084.59 | J21: Ferguson Q2 CY2026 deck, slide 7
A22: Industrial | B22: 0.07 | C22: 0.18 | D22: 0.06 | E22: =B22*$E$25 -> 584.01 | J22: Ferguson Q2 CY2026 deck, slide 7
A23: Facilities Supply | B23: 0.04 | C23: 0.05 | D23: 0.02 | E23: =B23*$E$25 -> 333.72 | J23: Ferguson Q2 CY2026 deck, slide 7
A24: Fire & Fabrication | B24: 0.02 | C24: -0.13 | D24: 0.05 | E24: =B24*$E$25 -> 166.86 | J24: Ferguson Q2 CY2026 deck, slide 7
A25: US total | B25: =SUM(B17:B24) -> 1 | C25: 0.05 | D25: 0.068 | E25: 8343 | J25: US segment net sales, quarter ended 30 June 2026
A26: Canada | C26: -0.019 | E26: 408 | J26: Canada segment, same quarter
A27: Group total | C27: 0.046 | E27: 8751 | J27: Quarter ended 30 June 2026
A29: Waterworks revenue — ESTIMATE, not a reported figure
A30: Step | B30: Value | C30: Unit | J30: Basis
A31: Group revenue, calendar 2025 | B31: 31316 | C31: $m | J31: Reported
A32: Canada, annualised from Q2 | B32: =E26*4 -> 1632 | C32: $m | J32: ESTIMATE — $408m x 4
A33: Implied US revenue | B33: =B31-B32 -> 29684 | C33: $m | J33: Formula
A34: Waterworks share — full-year low | B34: 0.22 | C34: % | J34: ESTIMATE. Q2 is seasonally the strongest waterworks quarter, so the reported 24% overstates the full-year share.
A35: Waterworks share — Q2 reported | B35: 0.24 | C35: % | J35: Reported
A36: Estimated waterworks revenue — low | B36: =B33*B34 -> 6530.48 | C36: $m | J36: Formula
A37: Estimated waterworks revenue — high | B37: =B33*B35 -> 7124.16 | C37: $m | J37: Formula
A38: as % of group revenue | B38: =B37/B31 -> 0.22749266 | C38: % | J38: Formula
A40: Other
A41: Item | B41: Value | C41: Unit | J41: Note
A42: Large capital projects, % of group revenue | B42: 0.07 | C42: % | J42: Mid- to high-single-digit and trending up. Backlogs building above realised growth rates, incl. waterworks.
A43: Commodities, % of revenue | B43: 0.15 | C43: % | J43: PVC still in double-digit deflation in Q2 CY26.
A44: FloWorks acquisition — price | B44: 1600 | C44: $m | J44: ~$1bn revenue; ~10x LTM adjusted EBITDA incl. synergies; expected close Q3 2026.
A45: FloWorks — expected annual synergies | B45: 45 | C45: $m | J45: Cross-sell into waterworks, commercial/mechanical and industrial.
A46: Net debt : adjusted EBITDA | B46: 1.3 | C46: x | J46: Target range 1-2x; ~1.8x expected at FloWorks closing.
A47: CY2026 operating margin guidance — low | B47: 0.095 | C47: % | J47: Raised at Q2.
A48: CY2026 operating margin guidance — high | B48: 0.098 | C48: %

Sheet Comparison
A1: Core & Main vs Ferguson
A2: Two very different ways to own the same theme. Sensitivity computed by formula.
A4: Side by side
A5: Metric | B5: Core & Main | C5: Ferguson | D5: Note
A6: Latest full-year revenue ($m) | B6: ='Core and Main'!F6 -> 7647 | C6: =Ferguson!I6 -> 31316 | D6: CNM: FY ended 1 Feb 2026. FERG: calendar 2025.
A7: Estimated waterworks revenue ($m) | B7: ='Core and Main'!F6 -> 7647 | C7: =Ferguson!B37 -> 7124.16 | D7: CNM is 100% water. FERG figure is an ESTIMATE — see Ferguson tab.
A8: as % of group revenue | B8: =B7/B6 -> 1 | C8: =C7/C6 -> 0.22749266 | D8: Formula
A9: Municipal revenue ($m) | B9: ='Core and Main'!C19 -> 3364.68 | C9: n/d | D9: Ferguson does not disclose a municipal split.
A10: as % of group revenue | B10: =B9/B6 -> 0.44 | C10: n/d | D10: Formula
A11: Profitability margin | B11: 0.122 | C11: 0.107 | D11: CNM adjusted EBITDA margin FY2025. FERG adjusted operating margin Q2 CY26 — not like for like.
A12: Repair & replace share | B12: 0.5 | C12: n/d | D12: CNM deck. Ferguson does not disclose.
A14: Combined market position
A15: Metric | B15: Value | D15: Basis
A16: Combined waterworks revenue ($m) | B16: =B7+C7 -> 14771.16 | D16: Formula
A17: US TAM ($m) | B17: ='Core and Main'!B30*1000 -> 39000 | D17: Core & Main deck
A18: Combined share of US TAM | B18: =B16/B17 -> 0.37874769 | D18: A duopoly at the head of a long fragmented tail — the structural reason both can consolidate and hold pricing.
A20: Sensitivity — what 100bp of market growth is actually worth
A21: Metric | B21: Core & Main | C21: Ferguson | D21: Note
A22: Exposed revenue base ($m) | B22: =B9 -> 3364.68 | C22: =C7 -> 7124.16 | D22: CNM: municipal revenue. FERG: estimated waterworks revenue.
A23: Market growth change | B23: 0.01 | C23: 0.01 | D23: Editable — change to test other increments.
A24: Revenue impact ($m) | B24: =B22*B23 -> 33.6468 | C24: =C22*C23 -> 71.2416 | D24: Formula
A25: as % of group revenue | B25: =B24/B6 -> 0.0044 | C25: =C24/C6 -> 0.0022749266 | D25: THE NUMBER MOST INVESTORS GET WRONG. Even for the pure play this is under half a percent.
A26: EBITDA impact ($m) | B26: =B24*B11 -> 4.1049096 | C26: =C24*C11 -> 7.6228512 | D26: At current margins. Incremental margin on distribution volume is typically higher.
A28: IIJA peak drag scenario | B28: Core & Main | C28: Ferguson | D28: Note
A29: Market growth points lost at peak | B29: 0.0125 | C29: 0.0125 | D29: Midpoint of the 1.0-1.5pt range, concentrated in 2029-2030 — see Forward Model.
A30: Revenue growth impact | B30: =B22*B29/B6 -> 0.0055 | C30: =C22*C29/C6 -> 0.0028436582 | D30: Formula. Well under 100bps for either company.
A32: Residential construction — 18% of Core & Main's mix and about half of Ferguson's US mix — moves both companies materially more than the federal funding question does. That is the risk worth underwriting.

Sheet Dashboard
A1: Dashboard
A2: Every figure below is a live link to the tab that derives it.
A4: The funding map
A5: Metric | B5: Value | C5: Unit | D5: Reads
A6: State and local share of water infrastructure | B6: ='Historical Spending'!B10 -> 114 | C6: % | D6: CBO. Federal policy sets rules far more powerfully than it sets budgets.
A7: Water utilities total spending, 2023 | B7: ='Historical Spending'!B7 -> 0.023 | C7: $bn | D7: CBO — of which capital is the minority.
A8: of which capital | B8: ='Historical Spending'!B8 -> 175 | C8: $bn | D8: The anchor for the forward model.
A9: Water and sewer bill increase, 2025 | B9: ='Historical Spending'!B44 -> 6.4 | C9: % | D9: Bluefield. The variable that matters most for distributor revenue.
A11: The forward model
A12: Metric | B12: Value | C12: Unit | D12: Reads
A13: 2026 capital base | B13: =Assumptions!B6 -> 68 | C13: $bn | D13: Reconciliation of four independent sources.
A14: 2030 total spending (base case) | B14: ='Forward Model'!G9 -> 82.391265 | C14: $bn
A15: 2035 total spending (base case) | B15: ='Forward Model'!L9 -> 97.35447 | C15: $bn
A16: CAGR 2026-2035 | B16: =('Forward Model'!L9/'Forward Model'!C9)^(1/9)-1 -> 0.040677899 | C16: % | D16: Mid-single-digit nominal. Not a boom and not a bust.
A17: Net IIJA drag as % of base | B17: =Assumptions!B11 -> 0.098529412 | C17: % | D17: The honest measure of the cliff — not the 100% often assumed.
A18: 2035 bear case | B18: =Scenarios!L5 -> 81.224577 | C18: $bn
A19: 2035 bull case | B19: =Scenarios!L7 -> 109.39841 | C19: $bn | D19: No credible scenario has spending falling in nominal terms.
A21: The engineering evidence
A22: Metric | B22: Value | C22: Unit | D22: Reads
A23: Cast iron vs PVC failure ratio | B23: ='Pipe and Assets'!B24 -> 9.862069 | C23: x | D23: The single most defensible number in the replacement case.
A24: Change in national break rate, 2018-2023 | B24: ='Pipe and Assets'!B23 -> -0.20714286 | C24: % | D24: THE COUNTER-EVIDENCE. The network is getting more reliable, not less.
A25: Lead service lines | B25: =Regulatory!B5 -> Value | C25: count | D25: Hard legal replacement mandate.
A26: Lead replacement unfunded balance | B26: =Regulatory!B11 -> 15 | C26: $bn | D26: Must come from rates. This is the rate-driver.
A28: The companies
A29: Metric | B29: Value | C29: Unit | D29: Reads
A30: Core & Main revenue ($m) | B30: =Comparison!B6 -> 7647 | C30: $m | D30: FY ended 1 Feb 2026.
A31: Ferguson revenue ($m) | B31: =Comparison!C6 -> 31316 | C31: $m | D31: Calendar 2025.
A32: Combined share of US TAM | B32: =Comparison!B18 -> 0.37874769 | C32: % | D32: A duopoly at the head of a fragmented tail.
A33: 100bp market growth — CNM revenue impact | B33: =Comparison!B25 -> 0.0044 | C33: % of sales | D33: The IIJA cliff is worth less than this to either company.
A34: 100bp market growth — FERG revenue impact | B34: =Comparison!C25 -> 0.0022749266 | C34: % of sales
A36: VERIFY BEFORE USE: public-sector figures in this workbook were obtained via search results summarising primary documents, because this environment's network policy blocked direct access to cbo.gov, epa.gov, census.gov, congress.gov and fred.stlouisfed.org. Company financials came from Quartr's primary filings and do not carry this caveat. See the Read Me tab.

Sheet Asset Data Sources
A1: Pipe Age and Repair History — What Is Public
A2: Where segment-level installation year and repair history can actually be obtained.
A4: The structural gap
A5: Sector | B5: National age registry? | C5: Granularity | D5: Publisher | E5: Note
A6: Natural gas + hazardous liquid | B6: YES | C6: National, by decade | D6: PHMSA | E6: By-Decade Inventory: mileage by decade of installation for gas distribution, gas transmission and hazardous liquid. Operators must file annual reports covering age, length, diameter, material.
A7: Water and wastewater | B7: NO | C7: None | D7: — | E7: No federal reporting requirement for pipe age. SDWIS carries compliance and violations but no distribution-system asset inventory. Responsibility sits with ~50,000 community water systems.
A8: CONSEQUENCE: every national water pipe-age figure in this workbook is a survey estimate, not a census. The USU study covers ~400,000 miles — over 17% of the 2.3m miles in the US and Canada.
A11: Tier 1 — asset-level and genuinely public
A12: Source type | B12: What it contains | C12: Granularity | D12: Cost | E12: Examples and caveats
A13: Municipal GIS open-data portals | B13: Water main layer: installation year, material, diameter, length, sometimes lining status | C13: Pipe segment | D13: Free | E13: Seattle Public Utilities Water Mains (incl. a 'Presumed Unlined' condition layer); Open Data DC; federated search via catalog.data.gov. THE BEST SOURCE FOR PIPE AGE. Install year often null on the oldest segments — precisely the ones that matter.
A14: Water main break datasets | B14: Break location and date | C14: Point location | D14: Free | E14: DC Water publishes five years of breaks, updated weekly. Records FAILURES, not planned replacement — a segment replaced on schedule generates no record.
A15: Street opening / excavation permits | B15: Who dug, where, when, why | C15: Street segment | D15: Free | E15: NYCStreets permit management; Chicago CDOT Office of Underground Coordination. The best available proxy for LAST PERIOD OF REPAIR, and it captures planned work that break data misses.
A16: Lead service line inventories | B16: Service line material by location incl. lead, galvanized-requiring-replacement and unknown | C16: Address / parcel | D16: Free | E16: Mandatory public accessibility since 16 Oct 2024; systems >50,000 must publish online. Baseline inventory and replacement plan due 1 Nov 2027, updated ANNUALLY. State dashboards: New York, Minnesota.
A18: Tier 2 — system-level, and the most useful for an investor
A19: Source type | B19: What it contains | C19: Granularity | D19: Cost | E19: Examples and caveats
A20: Municipal bond official statements | B20: System description: miles of main, material mix, age profile, capital plan, replacement rates, rate history | C20: Utility | D20: Free | E20: MSRB EMMA — official statements for essentially every muni bond since 1990, plus continuing disclosure. Disclosure liability compels the issuer to describe the asset. HIGHEST-DENSITY PUBLIC SOURCE.
A21: Asset management plans / CIPs | B21: Segment register with material, diameter, install year, replacement value, maintenance history; sequenced CIP | C21: Utility | D21: Free | E21: Published directly by some utilities, e.g. Sacramento Suburban Water District's Distribution Main Asset Management Plan. Availability is patchy.
A22: Investor-owned utility 10-Ks | B22: Replacement cycle, miles to be replaced, capital plans | C22: Company | D22: Free | E22: American Water: renewal rate improved from a 250-year cycle (2009) to ~125-year by 2028; ~2,000 miles 2024-2028; $34-38bn over ten years. An SEC filing, not an advocacy report.
A23: State PUC rate-case dockets | B23: Depreciation studies with assumed service lives by asset class; plant-in-service vintage | C23: Company / asset class | D23: Free | E23: Public docket filings, state by state.
A24: CSO / SSO consent decrees | B24: System condition assessments and dated remediation schedules | C24: System | D24: Free | E24: DOJ/EPA lodged decrees. Effectively a court-supervised published asset plan.
A26: Tier 3 — national aggregates (estimates, not censuses)
A27: Source | B27: What it gives | C27: Coverage | E27: Limitation
A28: USU Water Main Break Rates (Dec 2023) | B28: Break rate and age by material; avg failure age 53 yrs; 33% of mains >50 yrs | C28: 802 utilities, ~400,000 miles | E28: >17% of the 2.3m miles in US+Canada. Best available, still a sample.
A29: EPA CWNS 2022 | B29: FACILITY-LEVEL project and needs data, downloadable CSV or Access | C29: All states, 100% participation | E29: Projects and costs, NOT pipe age. Wastewater only.
A30: EPA 7th DWINSA | B30: National and state needs; 9.2m lead service lines | C30: National | E30: Aggregated. Underlying utility responses are not public.
A31: UMich Center for Sustainable Systems | B31: Average age of US water pipes 45 years (2020), up from 25 (1970) | C31: National | E31: Derived estimate, not a measurement.
A33: What does not exist
A34: Item | B34: Status | E34: Note
A35: Federal water analogue to PHMSA By-Decade Inventory | B35: DOES NOT EXIST | E35: No agency collects water pipe age.
A36: SDWIS distribution-system asset inventory | B36: DOES NOT EXIST | E36: SDWIS covers compliance, violations, enforcement and basic system inventory only.
A37: PIPEiD (Virginia Tech SWIM Center) | B37: EXISTS BUT NOT OPEN | E37: Bureau of Reclamation funded; data from 500+ US water utilities and 100 federal facilities. A SECURED utility decision-support platform, not an open dataset. Its existence is the clearest evidence the gap is real and recognised.
A38: AWIA s.2013 risk and resilience assessments | B38: CONFIDENTIAL BY STATUTE | E38: Deliberately withheld on security grounds.
A40: Recipe for a bottom-up demand estimate
A41: Step | B41: Action | E41: Output
A42: 1 | B42: Select the 20-30 utilities with the largest capital programmes | E42: Identifiable from EMMA issuance volume and CWNS project data
A43: 2 | B43: Pull each water main GIS layer; build a vintage histogram | E43: Miles by installation decade and material; implied replacement rate from year-on-year layer changes
A44: 3 | B44: Pull the EMMA official statement and CIP | E44: Stated forward capital plan; continuing disclosure gives actuals vs plan
A45: 4 | B45: Pull the LSL inventory, and from Nov 2027 the annual replacement plan | E45: Service line counts and realised replacement pace
A46: 5 | B46: Pull break datasets and street-opening permits | E46: Validation that stated replacement is physically happening
A48: LIMITATIONS. Coverage skews to large, well-resourced utilities — most of the ~50,000 community water systems publish nothing, so extrapolating from the transparent ones overstates system quality and understates need. Installation year is frequently null on the oldest segments. 'Last repair' is almost never an attribute — breaks and permits are proxies, and both miss trenchless rehabilitation such as CIPP lining and pipe bursting. Schemas are not standardised across utilities, which is the specific problem PIPEiD exists to solve and has not solved.
A50: VERIFICATION CAVEAT: none of these portals could be opened from the session that produced this workbook — the environment's egress allowlist blocks all external hosts. Descriptions are built from search evidence about what these sources contain, not from inspecting them. Confirm each dataset's actual schema, and how sparsely the installation-year field is populated, before relying on it.

Sheet Annual
A1: Annual Data — As Far Back As Available
A2: Company data downloaded from Quartr, one column per fiscal year. Macro data compiled with sources and retrieval routes. $m unless stated.
A4: Core & Main (CNM) — fiscal years ended the Sunday nearest 31 January
A5: $m | B5: FY2021 | C5: FY2022 | D5: FY2023 | E5: FY2024 | F5: FY2025 | K5: Source
A6: Period end | B6: 2022-01-30 | C6: 2023-01-29 | D6: 2024-01-28 | E6: 2025-02-02 | F6: 2026-02-01 | K6: Quartr, standardised from primary filings
A7: Net sales | B7: 5004 | C7: 6651 | D7: 6702 | E7: 7441 | F7: 7647 | K7: see period columns
A8: growth | C8: =C7/B7-1 -> 0.32913669 | D8: =D7/C7-1 -> 0.0076680198 | E8: =E7/D7-1 -> 0.11026559 | F8: =F7/E7-1 -> 0.027684451 | K8: Formula
A9: Gross profit | B9: 1280 | C9: 1795 | D9: 1818 | E9: 1980 | F9: 2059
A10: gross margin | B10: =B9/B7 -> 0.25579536 | C10: =C9/C7 -> 0.26988423 | D10: =D9/D7 -> 0.27126231 | E10: =E9/E7 -> 0.26609327 | F10: =F9/F7 -> 0.26925592 | K10: Formula
A11: EBITDA (standardised) | B11: 604 | C11: 918 | D11: 889 | E11: 905 | F11: 913 | K11: Company-reported Adjusted EBITDA for FY2025 was $931m
A12: EBITDA margin | B12: =B11/B7 -> 0.12070344 | C12: =C11/C7 -> 0.13802436 | D12: =D11/D7 -> 0.13264697 | E12: =E11/E7 -> 0.12162344 | F12: =F11/F7 -> 0.11939323 | K12: Formula
A13: Operating income | B13: 425 | C13: 775 | D13: 740 | E13: 719 | F13: 722
A14: Net income | B14: 225 | C14: 366 | D14: 371 | E14: 434 | F14: 462
A15: Diluted EPS ($) | B15: 0.55 | C15: 2.13 | D15: 2.15 | E15: 2.13 | F15: 2.31
A16: Cash from operations | B16: -31 | C16: 401 | D16: 1069 | E16: 621 | F16: 650
A17: Capital expenditure (abs) | B17: 20 | C17: 25 | D17: 39 | E17: 35 | F17: 46 | K17: Sign convention varies in the vendor feed; absolute values used
A18: Free cash flow | B18: =B16-B17 -> -51 | C18: =C16-C17 -> 376 | D18: =D16-D17 -> 1030 | E18: =E16-E17 -> 586 | F18: =F16-F17 -> 604 | K18: Formula: CFO less capex. Computed rather than taken from the vendor FCF field
A19: FCF conversion of EBITDA | B19: =IF(B11=0,0,B18/B11) -> -0.084437086 | C19: =IF(C11=0,0,C18/C11) -> 0.40958606 | D19: =IF(D11=0,0,D18/D11) -> 1.1586052 | E19: =IF(E11=0,0,E18/E11) -> 0.64751381 | F19: =IF(F11=0,0,F18/F11) -> 0.66155531 | K19: Formula
A20: Capex as % of sales | B20: =B17/B7 -> 0.0039968026 | C20: =C17/C7 -> 0.0037588333 | D20: =D17/D7 -> 0.0058191585 | E20: =E17/E7 -> 0.0047036689 | F20: =F17/F7 -> 0.0060154309 | K20: Formula. Asset-light distribution model
A22: Quartr's coverage of Core & Main begins with the fiscal year ended 30 January 2022. The company IPO'd in July 2021, so this is effectively the full listed history.
A24: Ferguson (FERG) — fiscal years ended 31 July through FY2025, then a 31 December year end
A25: $m | B25: FY2018 | C25: FY2019 | D25: FY2020 | E25: FY2021 | F25: FY2022 | G25: FY2023 | H25: FY2024 | I25: FY2025 | J25: CY2025 | K25: Source
A26: Period end | B26: 2018-07-31 | C26: 2019-07-31 | D26: 2020-07-31 | E26: 2021-07-31 | F26: 2022-07-31 | G26: 2023-07-31 | H26: 2024-07-31 | I26: 2025-07-31 | J26: 2025-12-31 | K26: Quartr, standardised from primary filings
A27: Net sales | B27: 20752 | C27: 22010 | D27: 21819 | E27: 22792 | F27: 28566 | G27: 29734 | H27: 29635 | I27: 30762 | J27: 31316
A28: growth | C28: =C27/B27-1 -> 0.060620663 | D28: =D27/C27-1 -> -0.0086778737 | E28: =E27/D27-1 -> 0.044594161 | F28: =F27/E27-1 -> 0.2533345 | G28: =G27/F27-1 -> 0.040887769 | H28: =H27/G27-1 -> -0.0033295218 | I28: =I27/H27-1 -> 0.038029357 | J28: =J27/I27-1 -> 0.018009232 | K28: Formula. CY2025 is a transition period — NOT comparable to the July years
A29: Gross profit | B29: 6044 | C29: 6458 | D29: 6421 | E29: 6980 | F29: 8756 | G29: 9025 | H29: 9053 | I29: 9435 | J29: 9708
A30: gross margin | B30: =B29/B27 -> 0.29124904 | C30: =C29/C27 -> 0.29341209 | D30: =D29/D27 -> 0.2942848 | E30: =E29/E27 -> 0.30624781 | F30: =F29/F27 -> 0.30651824 | G30: =G29/G27 -> 0.30352458 | H30: =H29/H27 -> 0.30548338 | I30: =I29/I27 -> 0.30670958 | J30: =J29/J27 -> 0.31000128 | K30: Formula
A31: EBITDA | B31: 1687 | D31: 1581 | E31: 2168 | F31: 3121 | G31: 2980 | H31: 2987 | I31: 2979 | J31: 3243 | K31: FY2019 not available in the vendor feed
A32: Operating income | B32: 1360 | C32: 1402 | D32: 1422 | E32: 2034 | F32: 2820 | G32: 2659 | H32: 2652 | I32: 2606 | J32: 2789
A33: operating margin | B33: =B32/B27 -> 0.065535852 | C33: =C32/C27 -> 0.063698319 | D33: =D32/D27 -> 0.065172556 | E33: =E32/E27 -> 0.089241839 | F33: =F32/F27 -> 0.098718757 | G33: =G32/G27 -> 0.089426246 | H33: =H32/H27 -> 0.08948878 | I33: =I32/I27 -> 0.084714908 | J33: =J32/J27 -> 0.089059905 | K33: Formula
A34: Net income | B34: 1267 | C34: 1108 | D34: 961 | E34: 1508 | F34: 2122 | G34: 1889 | H34: 1735 | I34: 1856 | J34: 2006
A35: Diluted EPS ($) | F35: 9.69 | G35: 9.12 | H35: 8.53 | I35: 9.32 | J35: 10.16 | K35: Pre-FY2022 EPS reflects the pre-US-listing share structure and is not comparable
A36: Cash from operations | B36: 1323 | C36: 1609 | D36: 1868 | E36: 1541 | F36: 1149 | G36: 2723 | H36: 1873 | I36: 1908 | J36: 2181
A37: Capital expenditure (abs) | B37: 265 | C37: 382 | D37: 215 | E37: 174 | F37: 290 | G37: 441 | H37: 372 | I37: 305 | J37: 354 | K37: Sign convention varies in the vendor feed; absolute values used
A38: Free cash flow | B38: =B36-B37 -> 1058 | C38: =C36-C37 -> 1227 | D38: =D36-D37 -> 1653 | E38: =E36-E37 -> 1367 | F38: =F36-F37 -> 859 | G38: =G36-G37 -> 2282 | H38: =H36-H37 -> 1501 | I38: =I36-I37 -> 1603 | J38: =J36-J37 -> 1827 | K38: Formula: CFO less capex. The vendor FCF field is unreliable for FY2024 and is not used
A39: Capex as % of sales | B39: =B37/B27 -> 0.012769854 | C39: =C37/C27 -> 0.017355747 | D39: =D37/D27 -> 0.0098537971 | E39: =E37/E27 -> 0.0076342576 | F39: =F37/F27 -> 0.010151929 | G39: =G37/G27 -> 0.014831506 | H39: =H37/H27 -> 0.012552725 | I39: =I37/I27 -> 0.00991483 | J39: =J37/J27 -> 0.011304126 | K39: Formula
A41: DATA QUALITY: Quartr's coverage of Ferguson begins with the fiscal year ended 31 July 2018. The company reported as a UK-listed group before its US primary listing, and moved from a July to a December year end in 2025 — so CY2025 is a transition period and its growth rate against FY2025 is not a like-for-like comparison. The FY2024 vendor cash-flow record also carries financing lines in thousands rather than millions; those lines are excluded here.
A44: Macro series — compiled, with source and retrieval route
A45: COMPILED, NOT DOWNLOADED. Direct retrieval was blocked from the build environment (see Read Me). Each row carries the publisher, a link, and the exact route to refresh it automatically — FRED series ID, CRS table reference or EPA data portal. Values are as published.
A47: Series | B47: Period | C47: Value | D47: Unit | J47: Source | K47: Link / retrieval route
A48: Public spending, transportation + water infrastructure | B48: 2023 | C48: 626 | D48: $bn | E48: link | J48: CBO, Public Spending on Transportation and Water Infrastructure 1956-2023 (Feb 2025) | K48: CBO publishes a supplementary data workbook with the full 1956-2023 series
A49: as % of GDP | B49: 2023 | C49: 0.023 | D49: % | E49: link | J49: CBO | K49: Same workbook
A50: Water utilities — total spending | B50: 2023 | C50: 175 | D50: $bn | E50: link | J50: CBO via USAFacts | K50: CBO supplementary workbook, water utilities series 1956-2023
A51: Water utilities — capital | B51: 2023 | C51: 59 | D51: $bn | E51: link | J51: CBO | K51: CBO supplementary workbook. ANCHOR FOR THE FORWARD MODEL BASE
A52: Water utilities — operations & maintenance | B52: 2023 | C52: 114 | D52: $bn | E52: link | J52: CBO | K52: CBO supplementary workbook
A53: State + local share of water infrastructure | B53: 2023 | C53: 0.92 | D53: % | E53: link | J53: CBO | K53: CBO supplementary workbook
A54: State + local share of all public infrastructure | B54: 2023 | C54: 0.79 | D54: % | E54: link | J54: CBO | K54: $494.2bn of $625.8bn
A55: O&M share of all public infrastructure spending | B55: 2023 | C55: 0.567 | D55: % | E55: link | J55: CBO | K55: $355bn of $625.8bn
A56: Construction put in place — water supply, total | B56: Jan-2026 SAAR | C56: 36.5 | D56: $bn | E56: link | J56: US Census Bureau C30 | K56: FRED series TLWSCONS (SAAR) / TLWSCON (NSA monthly, sum for annual)
A57: Construction put in place — water supply, public | B57: Jan-2026 SAAR | C57: 34.8 | D57: $bn | E57: link | J57: US Census Bureau C30 | K57: FRED series PBWSCONS (SAAR) / PBWSCON (NSA monthly). History from 2002
A58: Construction put in place — sewage & waste disposal, total | B58: Jan-2026 SAAR | C58: 54.3 | D58: $bn | E58: link | J58: US Census Bureau C30 | K58: FRED series TLSWDCONS / TLSWDCON. CAUTION: includes solid waste facilities
A59: Construction put in place — sewage & waste disposal, public | B59: Jan-2026 SAAR | C59: 53 | D59: $bn | E59: link | J59: US Census Bureau C30 | K59: FRED series PBSWGCONS / PBSWGCON
... A93: Water main break rate | B93: 2023 study | C93: 11.1 | D93: per 100 mi/yr | E93: link | J93: Utah State University | K93: 802 utilities, ~400,000 miles. -20.7% vs 2018
A94: Cast iron + asbestos cement share of installed mains | B94: 2018 study | C94: 0.41 | D94: % | E94: link | J94: Utah State University
A95: Cast iron + asbestos cement share of installed mains | B95: 2023 study | C95: 0.33 | D95: % | E95: link | J95: Utah State University | K95: -8pts in five years
A96: Average age of US water pipes | B96: 1970 | C96: 25 | D96: years | E96: link | J96: UMich Center for Sustainable Systems
A97: Average age of US water pipes | B97: 2020 | C97: 45 | D97: years | E97: link | J97: UMich Center for Sustainable Systems
A98: Per capita water withdrawal | B98: 2000 | C98: 140 | D98: gal/capita/day | E98: link | J98: USGS | K98: USGS publishes a five-yearly national compilation
A99: Per capita water withdrawal | B99: 2020 | C99: 127 | D99: gal/capita/day | E99: link | J99: USGS | K99: Five-yearly series
A100: Public-supply domestic per capita use | B100: 2010 | C100: 88 | D100: gal/day | E100: link | J100: USGS | K100: Circular 1441
A101: Public-supply domestic per capita use | B101: 2015 | C101: 82 | D101: gal/day | E101: link | J101: USGS | K101: Circular 1441
A102: Total US water withdrawals | B102: 2015 | C102: 322 | D102: bn gal/day | E102: link | J102: USGS | K102: -9% vs 2010
A103: US water + sewer bill increase | B103: 2025 | C103: 0.051 | D103: % | E103: link | J103: Bluefield Research rate index (50 cities) | K103: Subscription series
A104: cumulative five-year increase | B104: 2020-2025 | C104: 0.242 | D104: % | E104: link | J104: Bluefield Research | K104: Subscription
A105: water rates | B105: 2024-25 | C105: 0.06 | D105: % | E105: link | J105: Bluefield Research | K105: Subscription
A106: wastewater rates | B106: 2024-25 | C106: 0.048 | D106: % | E106: link | J106: Bluefield Research | K106: Subscription
A107: Non-revenue water — share of treated supply | B107: current | C107: 0.195 | D107: % | E107: link | J107: Bluefield Research
A108: Non-revenue water — lost revenue | B108: current | C108: 6.4 | D108: $bn p.a. | E108: link | J108: Bluefield Research

Sheet Quarterly
A1: Quarterly Data — As Far Back As Available
A2: Downloaded from Quartr. One row per reported quarter; $m unless stated. Filter with the header row.
A4: Core & Main (CNM)
A5: Fiscal quarter | B5: Period end | C5: Reported | D5: Net sales | E5: Gross profit | F5: Gross margin | G5: EBITDA | H5: Operating income | I5: Net income | J5: Diluted EPS | K5: TTM net sales | L5: Source
A6: Q2 FY2021 | B6: 2021-08-01 | C6: 2021-09-14 | D6: 1297.6 | E6: 325.2 | F6: =E6/D6 -> 0.25061652 | G6: 175 | H6: 99.8 | I6: 9.5 | J6: -0.14 | L6: report
A7: Q3 FY2021 | B7: 2021-10-31 | C7: 2021-12-07 | D7: 1404.8 | E7: 370.6 | F7: =E7/D7 -> 0.26380979 | G7: 183.3 | H7: 147.5 | I7: 64.4 | J7: 0.39 | L7: report
A8: Q4 FY2021 | B8: 2022-01-30 | C8: 2022-03-30 | D8: 1246 | E8: 327 | F8: =E8/D8 -> 0.26243981 | G8: 145 | H8: 109 | I8: 79 | J8: 0.28 | L8: report
A9: Q1 FY2022 | B9: 2022-05-01 | C9: 2022-06-14 | D9: 1598 | E9: 421 | F9: =E9/D9 -> 0.26345432 | G9: 216 | H9: 180 | I9: 86 | J9: 0.5 | K9: =SUM(D6:D9) -> 5546.4 | L9: report
A10: Q2 FY2022 | B10: 2022-07-31 | C10: 2022-09-13 | D10: 1861 | E10: 501 | F10: =E10/D10 -> 0.2692101 | G10: 271 | H10: 237 | I10: 115 | J10: 0.67 | K10: =SUM(D7:D10) -> 6109.8 | L10: report
A11: Q3 FY2022 | B11: 2022-10-30 | C11: 2022-12-13 | D11: 1818 | E11: 500 | F11: =E11/D11 -> 0.2750275 | G11: 344 | H11: 234 | I11: 111 | J11: 0.65 | K11: =SUM(D8:D11) -> 6523 | L11: report
A12: Q4 FY2022 | B12: 2023-01-29 | C12: 2023-03-28 | D12: 1374 | E12: 373 | F12: =E12/D12 -> 0.27147016 | G12: 160 | H12: 124 | I12: 84 | J12: 0.31 | K12: =SUM(D9:D12) -> 6651 | L12: report
A13: Q1 FY2023 | B13: 2023-04-30 | C13: 2023-06-06 | D13: 1574 | E13: 439 | F13: =E13/D13 -> 0.27890724 | G13: 217 | H13: 181 | I13: 86 | J13: 0.5 | K13: =SUM(D10:D13) -> 6627 | L13: report
A14: Q2 FY2023 | B14: 2023-07-30 | C14: 2023-09-06 | D14: 1861 | E14: 501 | F14: =E14/D14 -> 0.2692101 | G14: 301 | H14: 226 | I14: 110 | J14: 0.66 | K14: =SUM(D11:D14) -> 6627 | L14: report
A15: Q3 FY2023 | B15: 2023-10-29 | C15: 2023-12-05 | D15: 1827 | E15: 494 | F15: =E15/D15 -> 0.27038862 | G15: 255 | H15: 217 | I15: 112 | J15: 0.65 | K15: =SUM(D12:D15) -> 6636 | L15: report
A16: Q4 FY2023 | B16: 2024-01-28 | C16: 2024-03-19 | D16: 1440 | E16: 384 | F16: =E16/D16 -> 0.26666667 | G16: 154 | H16: 116 | I16: 63 | J16: 0.34 | K16: =SUM(D13:D16) -> 6702 | L16: report
A17: Q1 FY2024 | B17: 2024-05-05 | C17: 2024-06-04 | D17: 1741 | E17: 468 | F17: =E17/D17 -> 0.26881103 | G17: 212 | H17: 168 | I17: 95 | J17: 0.49 | K17: =SUM(D14:D17) -> 6869 | L17: report
A18: Q2 FY2024 | B18: 2024-08-04 | C18: 2024-09-04 | D18: 1964 | E18: 518 | F18: =E18/D18 -> 0.26374745 | G18: 250 | H18: 204 | I18: 126 | J18: 0.61 | K18: =SUM(D15:D18) -> 6972 | L18: report
A19: Q3 FY2024 | B19: 2024-11-03 | C19: 2024-12-03 | D19: 2038 | E19: 543 | F19: =E19/D19 -> 0.26643768 | G19: 367 | H19: 223 | I19: 140 | J19: 0.69 | K19: =SUM(D16:D19) -> 7183 | L19: report
A20: Q4 FY2024 | B20: 2025-02-02 | C20: 2025-03-25 | D20: 1698 | E20: 451 | F20: =E20/D20 -> 0.2656066 | G20: 318 | H20: 124 | I20: 67 | J20: 0.33 | K20: =SUM(D17:D20) -> 7441 | L20: report
... A25: Q1 FY2026 | B25: 2026-05-03 | C25: 2026-06-10 | D25: 1910 | E25: 520 | F25: =E25/D25 -> 0.27225131 | G25: 223 | H25: 177 | I25: 113 | J25: 0.57 | K25: =SUM(D22:D25) -> 7646 | L25: report
A27: Cross-foot check — quarters against the reported annual
A28: Fiscal year | B28: Sum of quarters | C28: Reported annual | D28: Difference | L28: Verdict
A29: FY2022 | B29: =SUM(D9:D12) -> 6651 | C29: =Annual!C7 -> 6651 | D29: =B29-C29 -> 0 | L29: =IF(ABS(D29)<0.5,"TIES","CHECK") -> TIES
A30: FY2023 | B30: =SUM(D13:D16) -> 6702 | C30: =Annual!D7 -> 6702 | D30: =B30-C30 -> 0 | L30: =IF(ABS(D30)<0.5,"TIES","CHECK") -> TIES
A31: FY2024 | B31: =SUM(D17:D20) -> 7441 | C31: =Annual!E7 -> 7441 | D31: =B31-C31 -> 0 | L31: =IF(ABS(D31)<0.5,"TIES","CHECK") -> TIES
A32: FY2025 | B32: =SUM(D21:D24) -> 7647 | C32: =Annual!F7 -> 7647 | D32: =B32-C32 -> 0 | L32: =IF(ABS(D32)<0.5,"TIES","CHECK") -> TIES
A33: Core & Main's fiscal 2021 is not shown here: Quartr's quarterly coverage starts at Q2 FY2021, so the four quarters do not sum to that year. From FY2022 onward every year ties exactly.
A36: Ferguson (FERG)
A37: Ferguson reported on a UK half-year basis before its US primary listing. In the vendor feed the pre-FY2022 'Q2' and 'Q4' rows are CUMULATIVE half-year and full-year figures, not discrete quarters, and are excluded below. Discrete quarterly reporting begins with the quarter ended 31 October 2021, and every fiscal year from FY2022 ties exactly to the reported annual.
A39: Fiscal quarter | B39: Period end | C39: Reported | D39: Net sales | E39: Gross profit | F39: Gross margin | G39: EBITDA | H39: Operating income | I39: Net income | J39: Diluted EPS | K39: TTM net sales | L39: Source
A40: Q1 2022 | B40: 2021-12-07 | C40: 2021-12-07 | D40: 6803 | E40: 2127 | F40: =IF(D40=0,0,E40/D40) -> 0.31265618 | G40: 814 | H40: 739 | I40: 560 | J40: 2.51 | L40: report
A41: Q2 2022 | B41: 2022-03-15 | C41: 2022-03-15 | D41: 6508 | F41: =IF(D41=0,0,E41/D41) -> 0 | G41: 648 | H41: 555 | I41: 436 | J41: 1.93 | L41: report
A42: Q3 2022 | B42: 2022-06-14 | C42: 2022-06-14 | D42: 7284 | E42: 2205 | F42: =IF(D42=0,0,E42/D42) -> 0.30271829 | G42: 795 | H42: 712 | I42: 546 | J42: 2.5 | L42: report
A43: Q4 2022 | B43: 2022-09-27 | C43: 2022-09-27 | D43: 7971 | E43: 2435 | F43: =IF(D43=0,0,E43/D43) -> 0.30548237 | G43: 896 | H43: 814 | I43: 580 | J43: 2.72 | K43: =SUM(D40:D43) -> 28566 | L43: report
A44: Q1 2023 | B44: 2022-12-06 | C44: 2022-12-06 | D44: 7931 | E44: 2421 | F44: =IF(D44=0,0,E44/D44) -> 0.30525785 | G44: 831 | H44: 831 | I44: 595 | J44: 2.84 | K44: =SUM(D41:D44) -> 29694 | L44: report
A45: Q2 2023 | B45: 2023-03-07 | C45: 2023-03-07 | D45: 6825 | E45: 2062 | F45: =IF(D45=0,0,E45/D45) -> 0.30212454 | G45: 711 | H45: 549 | I45: 374 | J45: 1.8 | K45: =SUM(D42:D45) -> 30011 | L45: report
A46: Q3 2023 | B46: 2023-06-06 | C46: 2023-06-06 | D46: 7140 | E46: 2140 | F46: =IF(D46=0,0,E46/D46) -> 0.29971989 | G46: 740 | H46: 497 | I46: 336 | J46: 1.63 | K46: =SUM(D43:D46) -> 29867 | L46: report
A47: Q4 2023 | B47: 2023-09-26 | C47: 2023-09-26 | D47: 7838 | E47: 2402 | F47: =IF(D47=0,0,E47/D47) -> 0.30645573 | G47: 858 | H47: 782 | I47: 584 | J47: 2.85 | K47: =SUM(D44:D47) -> 29734 | L47: report
A48: Q1 2024 | B48: 2023-12-05 | C48: 2023-12-05 | D48: 7708 | E48: 2331 | F48: =IF(D48=0,0,E48/D48) -> 0.30241308 | G48: 739 | H48: 739 | I48: 519 | J48: 2.54 | K48: =SUM(D45:D48) -> 29511 | L48: report
A49: Q2 2024 | B49: 2024-03-05 | C49: 2024-03-05 | D49: 6673 | E49: 2029 | F49: =IF(D49=0,0,E49/D49) -> 0.30406114 | G49: 640 | H49: 477 | I49: 322 | J49: 1.58 | K49: =SUM(D46:D49) -> 29359 | L49: report
A50: Q3 2024 | B50: 2024-06-04 | C50: 2024-06-04 | D50: 7308 | E50: 2232 | F50: =IF(D50=0,0,E50/D50) -> 0.30541872 | G50: 625 | H50: 625 | I50: 443 | J50: 2.18 | K50: =SUM(D47:D50) -> 29527 | L50: report
A51: Q4 2024 | B51: 2024-09-17 | C51: 2024-09-17 | D51: 7946 | E51: 2461 | F51: =IF(D51=0,0,E51/D51) -> 0.30971558 | G51: 906 | H51: 811 | I51: 451 | J51: 2.23 | K51: =SUM(D48:D51) -> 29635 | L51: report
A52: Q1 2025 | B52: 2024-12-10 | C52: 2024-12-10 | D52: 7772 | E52: 2340 | F52: =IF(D52=0,0,E52/D52) -> 0.3010808 | G52: 755 | H52: 665 | I52: 470 | J52: 2.34 | K52: =SUM(D49:D52) -> 29699 | L52: report
A53: Q2 2025 | B53: 2025-03-11 | C53: 2025-03-11 | D53: 6872 | E53: 2042 | F53: =IF(D53=0,0,E53/D53) -> 0.29714785 | G53: 592 | H53: 410 | I53: 276 | J53: 1.38 | K53: =SUM(D50:D53) -> 29898 | L53: report
A54: Q3 2025 | B54: 2025-06-03 | C54: 2025-06-03 | D54: 7621 | E54: 2359 | F54: =IF(D54=0,0,E54/D54) -> 0.30953943 | G54: 882 | H54: 606 | I54: 410 | J54: 2.07 | K54: =SUM(D51:D54) -> 30211 | L54: report
... A59: Q2 2026 | B59: 2026-08-10 | C59: 2026-08-10 | D59: 8751 | E59: 2712 | F59: =IF(D59=0,0,E59/D59) -> 0.30990744 | G59: 992 | H59: 893 | I59: 666 | J59: 3.43 | K59: =SUM(D56:D59) -> 24392 | L59: report
A61: Cross-foot check — quarters against the reported annual
A62: Fiscal year | B62: Sum of quarters | C62: Reported annual | D62: Difference | L62: Verdict
A63: FY2022 | B63: =SUM(D40:D43) -> 28566 | C63: =Annual!F27 -> 28566 | D63: =B63-C63 -> 0 | L63: =IF(ABS(D63)<1,"TIES","CHECK") -> TIES
A64: FY2023 | B64: =SUM(D44:D47) -> 29734 | C64: =Annual!G27 -> 29734 | D64: =B64-C64 -> 0 | L64: =IF(ABS(D64)<1,"TIES","CHECK") -> TIES
A65: FY2024 | B65: =SUM(D48:D51) -> 29635 | C65: =Annual!H27 -> 29635 | D65: =B65-C65 -> 0 | L65: =IF(ABS(D65)<1,"TIES","CHECK") -> TIES
A66: FY2025 | B66: =SUM(D52:D55) -> 30762 | C66: =Annual!I27 -> 30762 | D66: =B66-C66 -> 0 | L66: =IF(ABS(D66)<1,"TIES","CHECK") -> TIES
A67: The 'Transition Q' row is the quarter ended 31 October 2025, reported inside Ferguson's transition period as it moved to a calendar year end. It sits outside both FY2025 and CY2026 and is therefore excluded from the cross-foot checks above.
A70: Note on precision
A71: Core & Main's Q1 FY2026 and Q1 FY2025 net sales both round to $1.91bn and the vendor feed and the company's own deck differ by $1m on which quarter is which. The comparison is flat either way. Where a single million matters, go to the 10-Q linked in the Source column.

Sheet Series Links
A1: Time-Series Links
A2: Direct download endpoints. FRED CSV needs no API key. Run data/fetch_series.py to pull them all.
A4: NOT VERIFIED LIVE. Every FRED series ID below was confirmed against its FRED series page, but could not be fetched from the build environment (egress allowlist blocks fred.stlouisfed.org). Run python3 data/fetch_series.py --check on a networked machine to validate every ID and name any that fail.
A6: FRED series — one command downloads all of them
A7: Group | B7: Description | C7: Series ID | D7: Frequency | E7: Units | F7: From | G7: CSV | H7: Why it matters
A8: Construction spending | B8: Total Construction Spending: Water Supply | C8: TLWSCON | D8: Monthly | E8: $m, NSA | F8: 2002 | G8: csv | H8: Sum 12 months for a true annual figure. The headline water supply series.
A9: Construction spending | B9: Total Construction Spending: Water Supply | C9: TLWSCONS | D9: Monthly | E9: $m, SAAR | F9: 2002 | G9: csv | H9: Seasonally adjusted annual rate — the figure quoted in this analysis.
A10: Construction spending | B10: Total Public Construction Spending: Water Supply | C10: PBWSCON | D10: Monthly | E10: $m, NSA | F10: 2002 | G10: csv | H10: Public only. Private = total less public.
A11: Construction spending | B11: Total Public Construction Spending: Water Supply | C11: PBWSCONS | D11: Monthly | E11: $m, SAAR | F11: 2002 | G11: csv | H11: Public only, SAAR.
A12: Construction spending | B12: Total Construction Spending: Sewage and Waste Disposal | C12: TLSWDCON | D12: Monthly | E12: $m, NSA | F12: 2002 | G12: csv | H12: CAUTION: bundles solid waste facilities with sewerage.
A13: Construction spending | B13: Total Construction Spending: Sewage and Waste Disposal | C13: TLSWDCONS | D13: Monthly | E13: $m, SAAR | F13: 2002 | G13: csv | H13: Same caution. This is the $54.3bn figure in the analysis.
A14: Construction spending | B14: Total Public Construction Spending: Sewage and Waste Disposal | C14: PBSWGCON | D14: Monthly | E14: $m, NSA | F14: 2002 | G14: csv | H14: Public only.
A15: Construction spending | B15: Total Public Construction Spending: Sewage and Waste Disposal | C15: PBSWGCONS | D15: Monthly | E15: $m, SAAR | F15: 2002 | G15: csv | H15: Public only, SAAR.
A16: Construction spending | B16: Total Public Construction Spending: Water Supply | C16: MPCP14XXS | D16: Monthly | E16: $m, SAAR | F16: 2002 | G16: csv | H16: Census alternate identifier for the same concept — cross-check.
A17: Construction spending | B17: Total Public Construction Spending: Sewage and Waste Disposal | C17: MPCP13XXS | D17: Monthly | E17: $m, SAAR | F17: 2002 | G17: csv | H17: Census alternate identifier — cross-check.
A18: Water rates (CPI) | B18: CPI-U: Water and Sewer and Trash Collection Services | C18: CUSR0000SEHG | D18: Monthly | E18: Index, SA | F18: 1983 | G18: csv | H18: THE key public series for the rate thesis. Monthly, back to 1983, free.
... A30: Pipe prices (PPI) | B30: PPI: Cast Iron Pressure and Soil Pipe and Fittings, Except Ductile Pressure Pipe | C30: WPU10150227 | D30: Monthly | E30: Index | F30: varies | G30: csv | H30: Cast iron excluding ductile — cleanest split.
A32: Multiple series in one request: https://fred.stlouisfed.org/graph/fredgraph.csv?id=ID1,ID2,ID3
A35: Bulk data portals and primary documents
A36: Group | B36: Source | C36: Format | D36: Coverage | G36: Link | H36: Note
A37: Public spending | B37: CBO — Public Spending on Transportation and Water Infrastructure, 1956-2023 | C37: XLSX supplementary workbook | D37: 1956-2023 annual | G37: open | H37: THE anchor source. The page carries a supplementary data workbook with the full annual series by mode, split capital vs operations & maintenance and federal vs state/local. This is where the $59bn water utilities capital figure comes from.
A38: Public spending | B38: Census Bureau — Construction Spending (C30) historical time series | C38: XLSX / CSV | D38: 1993- monthly | G38: open | H38: Official source behind the FRED construction series. Longer history than FRED for some cuts.
A39: Public spending | B39: Census Bureau — Construction Spending landing page | C39: PDF / XLSX | D39: Monthly releases | G39: open | H39: Monthly release tables including water supply and sewage & waste disposal.
A40: Public spending | B40: US Conference of Mayors — 2025 Public Infrastructure Spending | C40: PDF | D40: 2012-2024 | G40: open | H40: Local-government-only capital spending on sewer and water supply, cumulative and annual.
A41: Federal programmes | B41: CRS IF13177 — FY2026 Appropriations for EPA Water Infrastructure Programs | C41: PDF / HTML | D41: FY2025-FY2026 | G41: open | H41: Table 1 has enacted appropriations by programme. The clean source for the SRF fiscal-year series.
A42: Federal programmes | B42: CRS IF12950 — EPA Water Infrastructure Programs and FY2025 Appropriations | C42: PDF / HTML | D42: FY2024-FY2025 | G42: open | H42: Table 1.
A43: Federal programmes | B43: CRS R47474 — Clean Water SRF Allotment Formula | C43: PDF / HTML | D43: Historical | G43: open | H43: Longer-run CWSRF appropriations history and the 1987 allotment formula.
A44: Federal programmes | B44: CRS R47878 — Drinking Water Infrastructure Needs | C44: PDF / HTML | D44: DWINSA vintages | G44: open | H44: Restates DWINSA in 2022 dollars ($648.8bn).
A45: Federal programmes | B45: CRS R48565 — Wastewater Infrastructure Funding | C45: PDF / HTML | D45: Historical | G45: open | H45: EPA wastewater needs table and affordability analysis.
A46: Federal programmes | B46: EPA — WIFIA closed loans | C46: HTML list | D46: 2018- | G46: open | H46: Loan-by-loan record: borrower, amount, project value, close date.
A47: Federal programmes | B47: EPA — Water Infrastructure Investments (BIL/IIJA) | C47: HTML / PDF | D47: FY2022-FY2026 | G47: open | H47: IIJA allocation by pot and by state.
... A68: Asset-level | B68: Minnesota — Lead Infrastructure Transparency Tool | C68: Web map | D68: 2024- | G68: open | H68: Address-level search.
A70: What is genuinely downloadable, ranked
A71: Rank | B71: Source | H71: What you get
A72: 1 | B72: FRED | H72: Every series above, CSV, no key, one command.
A73: 2 | B73: EPA CWNS 2022 facility-level data | H73: CSV or Access, nationwide or by state, with a data dictionary. The richest free dataset in the sector.
A74: 3 | B74: CBO supplementary workbook | H74: The full 1956-2023 annual series by mode, capital vs O&M, federal vs state/local. One XLSX behind publication 60874.
A75: 4 | B75: Census C30 historical time series | H75: Monthly construction spending back to 1993.
A76: 5 | B76: Municipal GIS portals | H76: Segment-level pipe age and material, utility by utility.
A77: 6 | B77: MSRB EMMA | H77: Free, and the densest utility-level asset and capital-plan disclosure available.
A79: What is not downloadable
A80: Item | B80: Status | H80: Note
A81: Bluefield rate index | B81: SUBSCRIPTION | H81: Free substitute: FRED CUSR0000SEHG01 (CPI water and sewerage maintenance).
A82: EPA DWINSA underlying responses | B82: NOT PUBLISHED | H82: Aggregated national and state figures only.
A83: AWIA risk and resilience assessments | B83: CONFIDENTIAL BY STATUTE | H83: Withheld on security grounds.
A84: PIPEiD | B84: SECURED PLATFORM | H84: Exists, but built for utility decision support, not open data.
A85: National water pipe age registry | B85: DOES NOT EXIST | H85: PHMSA's By-Decade Inventory is the gas-sector comparator showing exactly what water lacks.

Sheet Evidence and Monitor
A1: Evidence and What to Monitor
A2: Verbatim management commentary with deep links, the ranked monitoring list, and the tests that would falsify this analysis.
A4: Management commentary — verbatim, from the earnings calls
A5: Speaker | B5: Call | C5: Quotation | D5: Independent check | E5: Link
A6: Brad Cowles, President | B6: Core & Main, Q1 FY2026, 10 Jun 2026 | C6: “On IIJA, the remaining funding is expected to hit the state revolving funds this year. That doesn’t mean that there’s any cliff to the funding or there’s any end to the funding. A lot of the funding has already hit the state revolving funds. Only about a third or less of it has hit the municipality level yet. … A portion of that funding is in the grant form, and then the other portion is in low interest loans. A portion of that would get repaid back into those state revolving funds and used for future sources.” | D6: Drives the drawdown phasing on the Assumptions tab. Not independently verifiable — no public dataset tracks SRF disbursement to municipality level. Treat as management estimate. | E6: call
A7: Robyn Bradbury, CFO | B7: Core & Main, Q1 FY2026, 10 Jun 2026 | C7: “95% of the funding that municipalities use for their water infrastructure is state and local, and we think that those are really strong. We’re seeing municipalities increase water rates to their customers to be able to afford some of the upgrades. We’re seeing municipal bond growth and the municipal bond issuance that’s going out there.” | D7: VERIFIES. CBO puts the state and local share at 92-96%; Bluefield measures 2025 rate growth at +5.1%. Management and third-party data agree — raises the confidence weighting. | E7: call
A8: Brad Cowles, President | B8: Core & Main, Q1 FY2026, 10 Jun 2026 | C8: “This is just a sort of a non-discretionary investment that the municipalities they must do… We see it as a pretty durable long-term trend that is driving good growth for us.” (on treatment plant demand) | D8: Consistent with Bluefield: 79% of forecast treatment capex is rehabilitation of existing assets, not new build. | E8: call
A9: Mark Witkowski, CEO | B9: Core & Main, Q1 FY2026, 10 Jun 2026 | C9: “We’ve definitely been in a lull from an M&A standpoint… What we have seen, I’d say more recently, is a pretty notable uptick in the pipeline.” | D9: Unverifiable forward statement. Watch completed deal announcements against it. | E9: call
A10: Bill Brundage, CFO | B10: Ferguson, Q2 CY2026, 10 Aug 2026 | C10: “PVC is still very much in deflation. If you look in the quarter, PVC is still down about in the double-digit range for the quarter. As a basket, commodities were about flat in the quarter.” | D10: Checkable monthly via FRED PPI series WPU072106033 (plastics water pipe) — see the Series Links tab. | E10: call
A11: Bill Brundage, CFO | B11: Ferguson, Q2 CY2026, 10 Aug 2026 | C11: “The backlogs, the open orders continue to build, both if you look at commercial mechanical and industrial and even waterworks, which had a bit of a lumpier quarter this quarter… those backlogs continuing to be above what those growth rates were for the quarter.” | D11: Backlog is not disclosed as a number. Unverifiable — the reported +3% waterworks growth is the only hard datapoint. | E11: call
A12: Kevin Murphy, CEO | B12: Ferguson, Q2 CY2026, 10 Aug 2026 | C12: “We do see good, broad-based, large capital construction project growth. Data center construction activity continues to be the strength of that sector, but we’re also seeing good growth… in areas like power generation, in areas like chemical, food and beverage, general manufacturing, mining and minerals, obviously water and wastewater treatment.” | D12: Consistent with the reported segment table: Commercial/Mechanical +15%, Industrial +18%, Waterworks +3%. | E12: call
A14: Quotations are transcribed from the Quartr transcripts of the calls named. The 'independent check' column states whether each claim can be verified against a third-party source, because a claim that cannot be checked should carry less weight than one that can — regardless of how confidently it was delivered.
A17: What to monitor, ranked by signal value
A18: Indicator | B18: Frequency | C18: Why it matters | D18: Where | E18: Link
A19: 1. Water and sewer rate growth | B19: Monthly | C19: 95% of the funding. Ran +5.1% in 2025 and +24.2% over five years. A deceleration here matters more than anything Congress does. THE single most important series in this analysis. | D19: FRED CUSR0000SEHG01 | E19: open
A20: 2. AWWA v. EPA (Lead and Copper Rule Improvements) | B20: Event | C20: Oral argument expected Fall 2026. The largest binary swing factor — an adverse ruling on utility-controlled line replacement removes a multi-billion dollar annual programme from the forecast. | D20: NRDC court tracker | E20: open
A21: 3. WRDA 2026 → appropriations | B21: Annual | C21: Authorises $14bn/4yr CWSRF and $16.5bn/5yr DWSRF. Watch whether authorisation converts to appropriation; the FY2027 House bill proposes a 16% SRF cut. | D21: CRS IF13177 | E21: open
A22: 4. Construction put in place — water supply and sewage | B22: Monthly | C22: Leads distributor revenue by roughly two to four quarters. | D22: FRED TLWSCONS / TLSWDCONS | E22: open
A23: 5. PVC / plastics water pipe PPI | B23: Monthly | C23: Determines whether reported revenue growth reflects volume or price. Currently masking municipal volume strength at both companies. | D23: FRED WPU072106033 | E23: open
A24: 6. Municipal bond issuance, water and sewer | B24: Continuous | C24: The capital vehicle. Issuers deferred through the 2023-24 rate spike and have been returning. | D24: MSRB EMMA | E24: open
A25: 7. Residential construction | B25: Monthly | C25: 18% of Core & Main's mix and about half of Ferguson's US mix. The actual drag on both today — and far larger than the federal funding question. | D25: Census new residential construction | E25: open
A26: 8. Lead service line replacement plans | B26: Annual from Nov 2027 | C26: The LCRI requires publicly accessible replacement plans, updated annually. First rolling public record of realised replacement pace. | D26: EPA / state inventories | E26: open
A29: What would falsify this analysis
A30: The claim | B30: What would break it | C30: Where you would see it first
A31: The capital base is ~$68bn | B31: CBO's supplementary workbook showing water utilities capital materially away from $59bn in 2023, or a sewerage share of the Census category far from the assumed 65%. | C31: CBO publication 60874 workbook; Census C30 detail
A32: Market grows 3-5% nominal through 2035 | B32: Rate growth falling below ~3% for two consecutive years, which would break the organic growth assumption that does most of the work in the model. | C32: FRED CUSR0000SEHG01, year on year
A33: The IIJA cliff is worth under 100bps to either company | B33: Municipal revenue growth at Core & Main decelerating by more than ~2 points in 2029-30 without a residential or pricing explanation. | C33: CNM quarterly municipal end-market commentary
A34: Replacement demand is regulation-driven, not failure-driven | B34: An adverse AWWA v. EPA ruling followed by no slowdown in municipal volumes — which would mean decay, not mandates, was driving the spend after all. | C34: Court ruling, then two to three quarters of CNM municipal growth
A35: The network is getting more reliable, not less | B35: A fourth USU survey showing break rates rising again from the 2023 level of 11.1 per 100 miles. | C35: USU Buried Structures Laboratory, next survey vintage
A36: Both companies out-grow the market via share and M&A | B36: Organic growth persistently at or below the 3-5% market rate with no acceleration from treatment plant and metering. | C36: CNM initiative disclosure; FERG waterworks growth vs US non-resi

Sheet Sources
A1: Sources and Known Biases
A2: Every source with the interest of the party that produced it, so the reader can discount accordingly.
A4: Public spending — historical
A5: Publisher | B5: Document | C5: Date | D5: Known interest / bias
A6: CBO | B6: Public Spending on Transportation and Water Infrastructure, 1956 to 2023 | C6: Feb 2025 | D6: Non-partisan scorekeeper — the most neutral source in the sector. Caveat: 'water utilities' bundles supply and wastewater and includes O&M.
A7: USAFacts | B7: Summary of the CBO series | C7: 2025 | D7: Non-partisan aggregator. Used for the modal and capital/O&M breakdown.
A8: US Census Bureau | B8: Value of Construction Put in Place (C30) | C8: Monthly | D8: Official statistics, no advocacy. Caveat: 'sewage and waste disposal' bundles solid waste with sewerage, overstating the wastewater component.
A9: US Conference of Mayors | B9: 2025 Public Infrastructure Spending | C9: 2025 | D9: Municipal advocacy organisation — interest in demonstrating local fiscal burden.
A11: Federal programmes
A12: Publisher | B12: Document | C12: Date | D12: Known interest / bias
A13: CRS | B13: IF13177 — FY2026 Appropriations for EPA Water Infrastructure Programs | C13: 2026 | D13: Non-partisan congressional research. High reliability.
A14: CRS | B14: R48565 — Wastewater Infrastructure Funding | C14: 2025 | D14: Same.
A15: CRS | B15: R47878 — Drinking Water Infrastructure Needs | C15: 2024 | D15: Same. Source of the $648.8bn (2022 dollars) restatement of DWINSA.
A16: EPA | B16: Water Infrastructure Investments; BIL fact sheets; WIFIA announcements | C16: 2021-26 | D16: Agency communicating its own programme — presents funding favourably.
A17: National League of Cities | B17: Water infrastructure funding cliff advocacy | C17: May 2026 | D17: ADVOCACY — lobbying to extend federal funding. Source of the $2.7bn to $11.4bn framing; directionally verifiable but framed to maximise the cliff.
A18: Senate EPW | B18: Water Resources Development Act of 2026 | C18: Jul 2026 | D18: Primary legislative source. Authorisation is not appropriation.
A20: Needs estimates and forecasts
A21: Publisher | B21: Document | C21: Date | D21: Known interest / bias
A22: EPA | B22: 7th Drinking Water Infrastructure Needs Survey and Assessment | C22: Sep 2023 | D22: ALLOCATION INSTRUMENT. States self-report and the results drive their own funding formula — a structural incentive to report high. EPA concedes transmission and distribution is undercounted.
A23: EPA | B23: Clean Watersheds Needs Survey 2022 | C23: Apr 2024 | D23: Same structure. First survey with 100% state participation, which mechanically inflates the year-on-year increase.
A24: GAO | B24: GAO-24-106251 | C24: 2024 | D24: Independent auditor. CRITICAL of EPA's needs estimate and the 1987 CWSRF allocation formula. Used here as the counterweight.
A25: EPA Office of Inspector General | B25: Report on 7th DWINSA lead service line allotments | C25: 2024 | D25: Independent internal auditor. Also critical.
A26: ASCE | B26: 2025 Infrastructure Report Card — drinking water C-, wastewater D+ | C26: Mar 2025 | D26: PROFESSIONAL SOCIETY OF CIVIL ENGINEERS. Direct commercial interest in higher infrastructure spending. Grading methodology not externally audited.
A27: ASCE | B27: Bridging the Gap — $99bn/yr water gap | C27: 2024 | D27: Same. Uses a broader 'economic need' definition not comparable to EPA's eligible-need definition.
A28: AWWA | B28: Beyond the Replacement Era — $2.1-2.4tn / 25yr | C28: Mar 2026 | D28: WATER UTILITY TRADE ASSOCIATION. Interest in federal funding and in justifying rate increases to regulators. Broadest definition of the four; the 168% required increase should be read as a bargaining position.
A29: Bluefield Research | B29: Treatment capex, pipe capex, rate index, non-revenue water | C29: 2025-26 | D29: COMMERCIAL MARKET RESEARCH sold to vendors and investors. Interest in a large addressable market, but methodology is bottom-up from project pipelines and is the closest to a revenue-relevant forecast.
A30: McKinsey | B30: Water resilience: closing the funding gap for utilities | C30: 2024 | D30: Consultancy. Used only as a cross-check on total utility spending (~$183bn implied).
A32: Technical
A33: Publisher | B33: Document | C33: Date | D33: Known interest / bias
A34: Utah State University | B34: Water Main Break Rates in the USA and Canada | C34: Dec 2023 | D34: Academic, but distributed by pipe-manufacturer interests, and its material-by-material break rates favour PVC. It is also the best data available — and its finding that break rates FELL cuts against its own $452bn headline, which is a point in favour of the data's integrity.
A35: USGS | B35: Water Use in the United States | C35: 2015/2020 series | D35: Federal scientific agency. Neutral. Caveat: the national compilation is published on a five-year lag.
A36: Springer / ASM / EPA | B36: Peer-reviewed literature on graphitic corrosion and tuberculation | C36: various | D36: Neutral engineering literature.
A38: Regulatory
A39: Publisher | B39: Document | C39: Date | D39: Known interest / bias
A40: EPA | B40: Lead and Copper Rule Improvements — final Oct 2024 | C40: 2024-26 | D40: Primary rulemaking source.
A41: NRDC tracker | B41: American Water Works Association v. EPA | C41: 2026 | D41: Environmental advocacy organisation, used only for case status. Oral argument expected Fall 2026.
A42: Federal Register | B42: Extending the Compliance Deadline for the PFOA and PFOS MCLs | C42: 20 May 2026 | D42: Primary source.
A43: AWWA / Black & Veatch | B43: PFAS National Cost Model — >$50bn/20yr | C43: 2023 | D43: Trade-association cost model, produced to argue against a stricter rule.
A44: CRS | B44: R49057 — Data Centers and Water: FAQ | C44: Jul 2026 | D44: Non-partisan congressional research.
A46: Company data — all via Quartr
A47: Publisher | B47: Document | C47: Date | D47: Known interest / bias
A48: Core & Main | B48: Q1 FY2026 results and investor presentation | C48: 10 Jun 2026 | D48: Primary. Net sales, mix, TAM, guidance, management commentary on the IIJA cliff.
A49: Core & Main | B49: FY2025 full-year results | C49: 24 Mar 2026 | D49: Primary. Five-year income statement.
A50: Ferguson | B50: Q2 CY2026 results and presentation | C50: 10 Aug 2026 | D50: Primary. US customer-group table, segment revenue, FloWorks terms.
A51: Ferguson | B51: CY2025 transition-period results | C51: 24 Feb 2026 | D51: Primary. Eight-period income statement.
